Workbook

Sheet Leia-me
B1: Calculadora de ROI Perfecting
B2: Versão 4.1 | Baseada no motor auditado v3.1-trajectory-1
B3: Workbook interativo: insira os dados da sua operação de vendas e obtenha ROI, payback e análise de risco em tempo real.
B7: O QUE ESTE WORKBOOK FAZ
B8: Projeta o retorno financeiro da adoção de horas de roleplay da Perfecting para suas equipes de vendas.
B9: Todas as células calculadas são fórmulas Excel — altere qualquer input e os resultados atualizam em tempo real.
B10: COMO USAR
B11: 1. Aba Premissas: revise e ajuste parâmetros globais (encargos, tiers de precificação, deltas de cenário, etc.).
B12: 2. Aba Equipes: insira a configuração da conta e dados por equipe (uma equipe por coluna C-L).
B13: 3. Aba Motor: cálculo automático — NÃO EDITE. Mostra detalhes por equipe.
B14: 4. Aba Conta: precificação consolidada, ROI, payback, série de 12 meses, verificação de realismo.
B15: 5. Aba Comparação de Cenários: veja os 3 cenários lado a lado (Conservador / Realista / Otimista).
... B38: Assentos
B39: Estimativas | C39: Receita, ticket, conversão, margem, rampa, novos contratados, gerentes, salário, ciclo são estimativas (não dados de clientes)
B40: Habilitação compartilhada
B41: Contratual

Sheet Tabela de Preços por Tier
B1: Tabela de Preços por Tier — Perfecting AI
B2: Referência rápida de preços por volume de horas
B3: Cliente: [inserir nome do cliente]
B5: TABELA DE PREÇOS POR HORA
B6: Tier | C6: Limite Superior (h/mês) | D6: Preço (R$/h) | E6: Economia vs Tier 1 | F6: Plano | G6: Horas/Assento/Mês | H6: Assentos Necessários
B7: Tier 1 | C7: ≤ 262 | D7: 98 | E7: — | F7: Intensivo | G7: 8 | H7: =ROUNDUP(262/8,0)
B8: Tier 2 | C8: 263 – 656 | D8: 82 | E8: =1-D8/D7 | F8: Padrão | G8: 4 | H8: =ROUNDUP(656/4,0)
B9: Tier 3 | C9: 657 – 1.243 | D9: 70 | E9: =1-D9/D7 | F9: Leve | G9: 2 | H9: =ROUNDUP(1243/2,0)
B10: Tier 4 | C10: > 1.243 | D10: 60 | E10: =1-D10/D7 | F10: Personalizado | G10: Variável | H10: =ROUNDUP(1243/8,0)

Sheet Premissas
B1: Premissas e Constantes
B2: Fonte: COGS V1 (ratificado 14/08) | Ajustável pelo usuário
B3: Parâmetros declarados e constantes fixas para o motor de cálculo. Células azul-amarelo são editáveis.
B6: PREMISSAS DECLARADAS — EDITÁVEIS
B7: Parâmetro | C7: Valor | E7: Observações | F7: Observações
B8: ENCARGOS (multiplicador trabalhista) | C8: 1.75 | E8: Cada R$1 de salário custa R$1,75 para a empresa
B9: JORNADA (horas úteis do gerente/mês) | C9: 200 | E9: Horas úteis de um gerente de treinamento por mês
B10: FATOR_ESCOPO (fallback) | C10: 2.1 | E10: Horas de gerente por hora de prática — usado quando declarado fora do intervalo
B11: SUPERVISAO (residual) | C11: 0.25 | E11: Tempo do gerente que continua necessário com a Perfecting
B12: HAIRCUT_RAMPA | C12: 0.7 | E12: Desconto anti-otimismo no ganho de rampa
B13: HAIRCUT_CICLO | C13: 0.7 | E13: Desconto anti-otimismo no ganho de ciclo
B14: HAIRCUT_CONVERSAO | C14: 0.7 | E14: Desconto anti-otimismo no ganho de conversão
B15: PCT_EVENTO_SUBSTITUIVEL | C15: 0.5 | E15: Fração de um evento presencial que é camada de prática
B17: CONSTANTES FIXAS [ratificado 14/08]
B18: Parâmetro | C18: Valor | E18: Observações | F18: Observações
B19: DIAS_UTEIS_MES | C19: 22 | E19: Dias úteis por mês
B20: DIAS_UTEIS_ANO | C20: 264 | E20: Dias úteis por ano
B21: TAXA_MINIMA (piso mensal) | C21: 13000 | E21: Mensalidade mínima para a conta
B22: Fator de escopo — mínimo | C22: 0.25
B23: Fator de escopo — máximo | C23: 6
B24: Receita/vendedor — mínimo esperado
B25: Receita/vendedor — máximo esperado
B26: Limite de verificação de realismo | C26: 0.25 | E26: Ganhos de performance / margem atual — limite
B28: ESCADA PROGRESSIVA (R$/hora, marginal por tier)
B29: Tier | C29: Limite superior (h/mês) | E29: R$/hora
B30: Tier 1 — até 262 h | C30: 262 | E30: 98
B31: Tier 2 — 263 a 573 h | C31: 573 | E31: 82
B32: Tier 3 — 574 a 1.243 h | C32: 1243 | E32: 70
B33: Tier 4 — acima de 1.243 h | C33: 999999999 | E33: 60
B35: PLANOS (definem consumo, não precificação)
B36: Plano | C36: Horas/assento/mês
B37: Essencial | C37: 2
B38: Padrão | C38: 4
B39: Intensivo | C39: 8
B41: CENÁRIOS (deltas predefinidos)
B42: Cenário | C42: Delta Ticket | D42: Delta Rampa | E42: Delta Ciclo | F42: Delta Conv (p.p.)
B43: Conservador | C43: 0.05 | D43: 0.2 | E43: 0.05 | F43: 0.5
B44: Realista | C44: 0.15 | D44: 0.5 | E44: 0.15 | F44: 2.5
B45: Otimista | C45: 0.2 | D45: 0.65 | E45: 0.2 | F45: 3.5
B47: CONTRATOS (duração compra garantias, não preço)
B48: Duração | C48: Meses | D48: Desconto | F48: Observações
B49: 3 meses | C49: 3 | D49: 0 | E49: Sem compromisso; tarifa vigente na renovação
B50: 6 meses | C50: 6 | D50: 0 | E50: Meio ano de previsibilidade
B51: 12 meses | C51: 12 | D51: 0 | E51: Trava ajuste de tarifa
B52: 24 meses | C52: 24 | D52: 0 | E52: Trava tarifa + um passo de nível de serviço
B54: DELTAS DO CENÁRIO ATIVO (derivados da aba Equipes — não editar)
B55: Parâmetro | C55: Valor | E55: Fonte | F55: Source
B56: Delta ticket predefinido | C56: =INDEX(C43:C45,MATCH(Equipes!$C$7,B43:B45,0))
B57: Delta rampa predefinido | C57: =INDEX(D43:D45,MATCH(Equipes!$C$7,B43:B45,0))
B58: Delta ciclo predefinido | C58: =INDEX(E43:E45,MATCH(Equipes!$C$7,B43:B45,0))
B59: Delta conversão predefinido (p.p.) | C59: =INDEX(F43:F45,MATCH(Equipes!$C$7,B43:B45,0))
B61: LIMITES DE AJUSTE FINO
B62: Parâmetro | C62: Valor Máximo
B63: Delta ticket máximo | C63: 0.3
B64: Delta rampa máximo | C64: 0.8
B65: Delta ciclo máximo | C65: 0.3
B66: Delta conversão máximo (p.p.) | C66: 5
B68: COI — Constantes de Custo da Inação
B69: Delta de atingimento de quota (quota attainment, semanal vs trimestral) | C69: 0.29 | D69: p.p. | E69: MySalesCoach 2026
B70: Delta de retenção (com vs sem coaching) | C70: 0.4 | D70: p.p. | E70: MySalesCoach 2026: 74% vs 34%
B71: Fator de custo de substituição | C71: 1 | D71: × salário | E71: SHRM/Gallup: 50-150%. 1× = conservador
B72: Taxa de "sem decisão" (no decision) | C72: 0.5 | D72: % | E72: Dixon/McKenna HBR: 40-60%
B73: Horas de coaching mínimas/vendedor/mês | C73: 2 | D73: h/mês | E73: MySalesCoach 2026: mínimo para impacto

Sheet Equipes
B1: Equipes — Insira os Dados da Sua Operação de Vendas
B2: Preencha apenas as células amarelas | Fonte azul = seu input
B3: Insira uma equipe por coluna. Equipe sem vendedores é ignorada. Siga os passos numerados.
B6: CONFIGURAÇÃO DA CONTA
B7: Cenário da conta | L7: Conservador / Realista / Otimista
B8: Duração do contrato | L8: 3 / 6 / 12 / 24 months — buys guarantees, not discount
B9: Habilitação compartilhada? | L9: Yes = managers & counterfactual declared once, allocated by seller count
B10: Contratual da conta (se compartilhada) | L10: none / managers / external / event
B11: N. gerentes de treinamento (conta) | L11: allocated by number of sellers
B12: Horas treinamento/gerente/mês (conta) | L12: per manager — NOT allocated
B13: Salário mensal do gerente (conta) | L13: per manager — NOT allocated
B14: Custo anual treinamento externo (conta) | L14: allocated by number of sellers
B15: Custo anual evento presencial (conta) | L15: allocated by number of sellers
B17: EQUIPES — UMA POR COLUNA. Equipe sem vendedores é ignorada.
B18: Nome da equipe
B20: Passo 1 Estrutura da Equipe
B21: Número de vendedores
B22: Número de gerentes de treinamento
B23: Horas de treinamento por gerente/mês
B24: Vendedores cobertos por gerente/mês
B25: Horas de prática por vendedor coberto (hoje)
B26: Salário mensal do gerente
B28: Passo 2 Receita
B29: Receita mensal da equipe
B30: Ticket médio
... B57: Delta conversão p.p. ajuste fino (0-5 p.p.)

Sheet Motor
B1: Motor — Cálculos Automatizados
B2: NÃO EDITE | Todos os valores são fórmulas
B3: Cálculos detalhados por equipe. Resultados só aparecem quando a equipe está completa.
B6: PARÂMETROS DERIVADOS
B7: Equipe ativa? | C7: =Equipes!C21>0 | D7: =Equipes!D21>0 | E7: =Equipes!E21>0 | F7: =Equipes!F21>0 | G7: =Equipes!G21>0 | H7: =Equipes!H21>0 | I7: =Equipes!I21>0 | J7: =Equipes!J21>0 | ... L7: =Equipes!L21>0
B8: Proporção de vendedores (se habilitação compart.) | C8: =IF(Equipes!$C$9="Sim",IF(SUM(Equipes!$C21:$L21)>0,IF(Equipes!C21>0,Equipes!C21/SUM(Equipes!$C21:$L21),""),""),1) | D8: =IF(Equipes!$C$9="Sim",IF(SUM(Equipes!$C21:$L21)>0,IF(Equipes!D21>0,Equipes!D21/SUM(Equipes!$C21:$L21),""),""),1) | E8: =IF(Equipes!$C$9="Sim",IF(SUM(Equipes!$C21:$L21)>0,IF(Equipes!E21>0,Equipes!E21/SUM(Equipes!$C21:$L21),""),""),1) | F8: =IF(Equipes!$C$9="Sim",IF(SUM(Equipes!$C21:$L21)>0,IF(Equipes!F21>0,Equipes!F21/SUM(Equipes!$C21:$L21),""),""),1) | G8: =IF(Equipes!$C$9="Sim",IF(SUM(Equipes!$C21:$L21)>0,IF(Equipes!G21>0,Equipes!G21/SUM(Equipes!$C21:$L21),""),""),1) | H8: =IF(Equipes!$C$9="Sim",IF(SUM(Equipes!$C21:$L21)>0,IF(Equipes!H21>0,Equipes!H21/SUM(Equipes!$C21:$L21),""),""),1) | I8: =IF(Equipes!$C$9="Sim",IF(SUM(Equipes!$C21:$L21)>0,IF(Equipes!I21>0,Equipes!I21/SUM(Equipes!$C21:$L21),""),""),1) | J8: =IF(Equipes!$C$9="Sim",IF(SUM(Equipes!$C21:$L21)>0,IF(Equipes!J21>0,Equipes!J21/SUM(Equipes!$C21:$L21),""),""),1) | ... L8: =IF(Equipes!$C$9="Sim",IF(SUM(Equipes!$C21:$L21)>0,IF(Equipes!L21>0,Equipes!L21/SUM(Equipes!$C21:$L21),""),""),1)
B9: Gerentes de treinamento | C9: =IF(Equipes!$C$9="Sim",IF(AND(N(Equipes!$C$11)>0,ISNUMBER(C8)),Equipes!$C$11*C8,""),IF(Equipes!C22="","",Equipes!C22)) | D9: =IF(Equipes!$C$9="Sim",IF(AND(N(Equipes!$C$11)>0,ISNUMBER(D8)),Equipes!$C$11*D8,""),IF(Equipes!D22="","",Equipes!D22)) | E9: =IF(Equipes!$C$9="Sim",IF(AND(N(Equipes!$C$11)>0,ISNUMBER(E8)),Equipes!$C$11*E8,""),IF(Equipes!E22="","",Equipes!E22)) | F9: =IF(Equipes!$C$9="Sim",IF(AND(N(Equipes!$C$11)>0,ISNUMBER(F8)),Equipes!$C$11*F8,""),IF(Equipes!F22="","",Equipes!F22)) | G9: =IF(Equipes!$C$9="Sim",IF(AND(N(Equipes!$C$11)>0,ISNUMBER(G8)),Equipes!$C$11*G8,""),IF(Equipes!G22="","",Equipes!G22)) | H9: =IF(Equipes!$C$9="Sim",IF(AND(N(Equipes!$C$11)>0,ISNUMBER(H8)),Equipes!$C$11*H8,""),IF(Equipes!H22="","",Equipes!H22)) | I9: =IF(Equipes!$C$9="Sim",IF(AND(N(Equipes!$C$11)>0,ISNUMBER(I8)),Equipes!$C$11*I8,""),IF(Equipes!I22="","",Equipes!I22)) | J9: =IF(Equipes!$C$9="Sim",IF(AND(N(Equipes!$C$11)>0,ISNUMBER(J8)),Equipes!$C$11*J8,""),IF(Equipes!J22="","",Equipes!J22)) | ... L9: =IF(Equipes!$C$9="Sim",IF(AND(N(Equipes!$C$11)>0,ISNUMBER(L8)),Equipes!$C$11*L8,""),IF(Equipes!L22="","",Equipes!L22))
B10: Horas de treinamento/gerente/mês | C10: =IF(Equipes!$C$9="Sim",IF(Equipes!$C$12="","",Equipes!$C$12),IF(Equipes!C23="","",Equipes!C23)) | D10: =IF(Equipes!$C$9="Sim",IF(Equipes!$C$12="","",Equipes!$C$12),IF(Equipes!D23="","",Equipes!D23)) | E10: =IF(Equipes!$C$9="Sim",IF(Equipes!$C$12="","",Equipes!$C$12),IF(Equipes!E23="","",Equipes!E23)) | F10: =IF(Equipes!$C$9="Sim",IF(Equipes!$C$12="","",Equipes!$C$12),IF(Equipes!F23="","",Equipes!F23)) | G10: =IF(Equipes!$C$9="Sim",IF(Equipes!$C$12="","",Equipes!$C$12),IF(Equipes!G23="","",Equipes!G23)) | H10: =IF(Equipes!$C$9="Sim",IF(Equipes!$C$12="","",Equipes!$C$12),IF(Equipes!H23="","",Equipes!H23)) | I10: =IF(Equipes!$C$9="Sim",IF(Equipes!$C$12="","",Equipes!$C$12),IF(Equipes!I23="","",Equipes!I23)) | J10: =IF(Equipes!$C$9="Sim",IF(Equipes!$C$12="","",Equipes!$C$12),IF(Equipes!J23="","",Equipes!J23)) | ... L10: =IF(Equipes!$C$9="Sim",IF(Equipes!$C$12="","",Equipes!$C$12),IF(Equipes!L23="","",Equipes!L23))
B11: Salário mensal do gerente | C11: =IF(Equipes!$C$9="Sim",IF(Equipes!$C$13="","",Equipes!$C$13),IF(Equipes!C26="","",Equipes!C26)) | D11: =IF(Equipes!$C$9="Sim",IF(Equipes!$C$13="","",Equipes!$C$13),IF(Equipes!D26="","",Equipes!D26)) | E11: =IF(Equipes!$C$9="Sim",IF(Equipes!$C$13="","",Equipes!$C$13),IF(Equipes!E26="","",Equipes!E26)) | F11: =IF(Equipes!$C$9="Sim",IF(Equipes!$C$13="","",Equipes!$C$13),IF(Equipes!F26="","",Equipes!F26)) | G11: =IF(Equipes!$C$9="Sim",IF(Equipes!$C$13="","",Equipes!$C$13),IF(Equipes!G26="","",Equipes!G26)) | H11: =IF(Equipes!$C$9="Sim",IF(Equipes!$C$13="","",Equipes!$C$13),IF(Equipes!H26="","",Equipes!H26)) | I11: =IF(Equipes!$C$9="Sim",IF(Equipes!$C$13="","",Equipes!$C$13),IF(Equipes!I26="","",Equipes!I26)) | J11: =IF(Equipes!$C$9="Sim",IF(Equipes!$C$13="","",Equipes!$C$13),IF(Equipes!J26="","",Equipes!J26)) | ... L11: =IF(Equipes!$C$9="Sim",IF(Equipes!$C$13="","",Equipes!$C$13),IF(Equipes!L26="","",Equipes!L26))
B12: Tipo contratual | C12: =IF(Equipes!$C$9="Sim",IF(Equipes!$C$10="","",Equipes!$C$10),IF(Equipes!C40="","",Equipes!C40)) | D12: =IF(Equipes!$C$9="Sim",IF(Equipes!$C$10="","",Equipes!$C$10),IF(Equipes!D40="","",Equipes!D40)) | E12: =IF(Equipes!$C$9="Sim",IF(Equipes!$C$10="","",Equipes!$C$10),IF(Equipes!E40="","",Equipes!E40)) | F12: =IF(Equipes!$C$9="Sim",IF(Equipes!$C$10="","",Equipes!$C$10),IF(Equipes!F40="","",Equipes!F40)) | G12: =IF(Equipes!$C$9="Sim",IF(Equipes!$C$10="","",Equipes!$C$10),IF(Equipes!G40="","",Equipes!G40)) | H12: =IF(Equipes!$C$9="Sim",IF(Equipes!$C$10="","",Equipes!$C$10),IF(Equipes!H40="","",Equipes!H40)) | I12: =IF(Equipes!$C$9="Sim",IF(Equipes!$C$10="","",Equipes!$C$10),IF(Equipes!I40="","",Equipes!I40)) | J12: =IF(Equipes!$C$9="Sim",IF(Equipes!$C$10="","",Equipes!$C$10),IF(Equipes!J40="","",Equipes!J40)) | ... L12: =IF(Equipes!$C$9="Sim",IF(Equipes!$C$10="","",Equipes!$C$10),IF(Equipes!L40="","",Equipes!L40))
B13: Custo anual treinamento externo (conta) | C13: =IF(Equipes!$C$9="Sim",IF(AND(N(Equipes!$C$14)>0,ISNUMBER(C8)),Equipes!$C$14*C8,""),IF(Equipes!C41="","",Equipes!C41)) | D13: =IF(Equipes!$C$9="Sim",IF(AND(N(Equipes!$C$14)>0,ISNUMBER(D8)),Equipes!$C$14*D8,""),IF(Equipes!D41="","",Equipes!D41)) | E13: =IF(Equipes!$C$9="Sim",IF(AND(N(Equipes!$C$14)>0,ISNUMBER(E8)),Equipes!$C$14*E8,""),IF(Equipes!E41="","",Equipes!E41)) | F13: =IF(Equipes!$C$9="Sim",IF(AND(N(Equipes!$C$14)>0,ISNUMBER(F8)),Equipes!$C$14*F8,""),IF(Equipes!F41="","",Equipes!F41)) | G13: =IF(Equipes!$C$9="Sim",IF(AND(N(Equipes!$C$14)>0,ISNUMBER(G8)),Equipes!$C$14*G8,""),IF(Equipes!G41="","",Equipes!G41)) | H13: =IF(Equipes!$C$9="Sim",IF(AND(N(Equipes!$C$14)>0,ISNUMBER(H8)),Equipes!$C$14*H8,""),IF(Equipes!H41="","",Equipes!H41)) | I13: =IF(Equipes!$C$9="Sim",IF(AND(N(Equipes!$C$14)>0,ISNUMBER(I8)),Equipes!$C$14*I8,""),IF(Equipes!I41="","",Equipes!I41)) | J13: =IF(Equipes!$C$9="Sim",IF(AND(N(Equipes!$C$14)>0,ISNUMBER(J8)),Equipes!$C$14*J8,""),IF(Equipes!J41="","",Equipes!J41)) | ... L13: =IF(Equipes!$C$9="Sim",IF(AND(N(Equipes!$C$14)>0,ISNUMBER(L8)),Equipes!$C$14*L8,""),IF(Equipes!L41="","",Equipes!L41))
B14: Custo anual evento presencial (conta) | C14: =IF(Equipes!$C$9="Sim",IF(AND(N(Equipes!$C$15)>0,ISNUMBER(C8)),Equipes!$C$15*C8,""),IF(Equipes!C42="","",Equipes!C42)) | D14: =IF(Equipes!$C$9="Sim",IF(AND(N(Equipes!$C$15)>0,ISNUMBER(D8)),Equipes!$C$15*D8,""),IF(Equipes!D42="","",Equipes!D42)) | E14: =IF(Equipes!$C$9="Sim",IF(AND(N(Equipes!$C$15)>0,ISNUMBER(E8)),Equipes!$C$15*E8,""),IF(Equipes!E42="","",Equipes!E42)) | F14: =IF(Equipes!$C$9="Sim",IF(AND(N(Equipes!$C$15)>0,ISNUMBER(F8)),Equipes!$C$15*F8,""),IF(Equipes!F42="","",Equipes!F42)) | G14: =IF(Equipes!$C$9="Sim",IF(AND(N(Equipes!$C$15)>0,ISNUMBER(G8)),Equipes!$C$15*G8,""),IF(Equipes!G42="","",Equipes!G42)) | H14: =IF(Equipes!$C$9="Sim",IF(AND(N(Equipes!$C$15)>0,ISNUMBER(H8)),Equipes!$C$15*H8,""),IF(Equipes!H42="","",Equipes!H42)) | I14: =IF(Equipes!$C$9="Sim",IF(AND(N(Equipes!$C$15)>0,ISNUMBER(I8)),Equipes!$C$15*I8,""),IF(Equipes!I42="","",Equipes!I42)) | J14: =IF(Equipes!$C$9="Sim",IF(AND(N(Equipes!$C$15)>0,ISNUMBER(J8)),Equipes!$C$15*J8,""),IF(Equipes!J42="","",Equipes!J42)) | ... L14: =IF(Equipes!$C$9="Sim",IF(AND(N(Equipes!$C$15)>0,ISNUMBER(L8)),Equipes!$C$15*L8,""),IF(Equipes!L42="","",Equipes!L42))
B15: Equipe completa? | C15: =AND(Equipes!C21>0,N(C9)>0,N(C10)>0,Equipes!C24>0,Equipes!C25>0,N(C11)>0,Equipes!C29>0,Equipes!C30>0,Equipes!C31>0,Equipes!C32>0,Equipes!C35>0,Equipes!C36>0,Equipes!C50>0,Equipes!C49<>"",C12<>"",IF(C12="treinamento externo",N(C13)>0,TRUE())) | D15: =AND(Equipes!D21>0,N(D9)>0,N(D10)>0,Equipes!D24>0,Equipes!D25>0,N(D11)>0,Equipes!D29>0,Equipes!D30>0,Equipes!D31>0,Equipes!D32>0,Equipes!D35>0,Equipes!D36>0,Equipes!D50>0,Equipes!D49<>"",D12<>"",IF(D12="treinamento externo",N(D13)>0,TRUE())) | E15: =AND(Equipes!E21>0,N(E9)>0,N(E10)>0,Equipes!E24>0,Equipes!E25>0,N(E11)>0,Equipes!E29>0,Equipes!E30>0,Equipes!E31>0,Equipes!E32>0,Equipes!E35>0,Equipes!E36>0,Equipes!E50>0,Equipes!E49<>"",E12<>"",IF(E12="treinamento externo",N(E13)>0,TRUE())) | F15: =AND(Equipes!F21>0,N(F9)>0,N(F10)>0,Equipes!F24>0,Equipes!F25>0,N(F11)>0,Equipes!F29>0,Equipes!F30>0,Equipes!F31>0,Equipes!F32>0,Equipes!F35>0,Equipes!F36>0,Equipes!F50>0,Equipes!F49<>"",F12<>"",IF(F12="treinamento externo",N(F13)>0,TRUE())) | G15: =AND(Equipes!G21>0,N(G9)>0,N(G10)>0,Equipes!G24>0,Equipes!G25>0,N(G11)>0,Equipes!G29>0,Equipes!G30>0,Equipes!G31>0,Equipes!G32>0,Equipes!G35>0,Equipes!G36>0,Equipes!G50>0,Equipes!G49<>"",G12<>"",IF(G12="treinamento externo",N(G13)>0,TRUE())) | H15: =AND(Equipes!H21>0,N(H9)>0,N(H10)>0,Equipes!H24>0,Equipes!H25>0,N(H11)>0,Equipes!H29>0,Equipes!H30>0,Equipes!H31>0,Equipes!H32>0,Equipes!H35>0,Equipes!H36>0,Equipes!H50>0,Equipes!H49<>"",H12<>"",IF(H12="treinamento externo",N(H13)>0,TRUE())) | I15: =AND(Equipes!I21>0,N(I9)>0,N(I10)>0,Equipes!I24>0,Equipes!I25>0,N(I11)>0,Equipes!I29>0,Equipes!I30>0,Equipes!I31>0,Equipes!I32>0,Equipes!I35>0,Equipes!I36>0,Equipes!I50>0,Equipes!I49<>"",I12<>"",IF(I12="treinamento externo",N(I13)>0,TRUE())) | J15: =AND(Equipes!J21>0,N(J9)>0,N(J10)>0,Equipes!J24>0,Equipes!J25>0,N(J11)>0,Equipes!J29>0,Equipes!J30>0,Equipes!J31>0,Equipes!J32>0,Equipes!J35>0,Equipes!J36>0,Equipes!J50>0,Equipes!J49<>"",J12<>"",IF(J12="treinamento externo",N(J13)>0,TRUE())) | ... L15: =AND(Equipes!L21>0,N(L9)>0,N(L10)>0,Equipes!L24>0,Equipes!L25>0,N(L11)>0,Equipes!L29>0,Equipes!L30>0,Equipes!L31>0,Equipes!L32>0,Equipes!L35>0,Equipes!L36>0,Equipes!L50>0,Equipes!L49<>"",L12<>"",IF(L12="treinamento externo",N(L13)>0,TRUE()))
B17: Horas de prática declaradas/mês
B18: Horas de prática com Perfecting/mês | C18: =IF(Equipes!C49="","",IFERROR(INDEX(Premissas!$C$37:$C$39,MATCH(Equipes!C49,Premissas!$B$37:$B$39,0)),"")) | D18: =IF(Equipes!D49="","",IFERROR(INDEX(Premissas!$C$37:$C$39,MATCH(Equipes!D49,Premissas!$B$37:$B$39,0)),"")) | E18: =IF(Equipes!E49="","",IFERROR(INDEX(Premissas!$C$37:$C$39,MATCH(Equipes!E49,Premissas!$B$37:$B$39,0)),"")) | F18: =IF(Equipes!F49="","",IFERROR(INDEX(Premissas!$C$37:$C$39,MATCH(Equipes!F49,Premissas!$B$37:$B$39,0)),"")) | G18: =IF(Equipes!G49="","",IFERROR(INDEX(Premissas!$C$37:$C$39,MATCH(Equipes!G49,Premissas!$B$37:$B$39,0)),"")) | H18: =IF(Equipes!H49="","",IFERROR(INDEX(Premissas!$C$37:$C$39,MATCH(Equipes!H49,Premissas!$B$37:$B$39,0)),"")) | I18: =IF(Equipes!I49="","",IFERROR(INDEX(Premissas!$C$37:$C$39,MATCH(Equipes!I49,Premissas!$B$37:$B$39,0)),"")) | J18: =IF(Equipes!J49="","",IFERROR(INDEX(Premissas!$C$37:$C$39,MATCH(Equipes!J49,Premissas!$B$37:$B$39,0)),"")) | ... L18: =IF(Equipes!L49="","",IFERROR(INDEX(Premissas!$C$37:$C$39,MATCH(Equipes!L49,Premissas!$B$37:$B$39,0)),""))
B19: Assentos efetivos | C19: =IF(C15,MIN(Equipes!C50,Equipes!C21),"") | D19: =IF(D15,MIN(Equipes!D50,Equipes!D21),"") | E19: =IF(E15,MIN(Equipes!E50,Equipes!E21),"") | F19: =IF(F15,MIN(Equipes!F50,Equipes!F21),"") | G19: =IF(G15,MIN(Equipes!G50,Equipes!G21),"") | H19: =IF(H15,MIN(Equipes!H50,Equipes!H21),"") | I19: =IF(I15,MIN(Equipes!I50,Equipes!I21),"") | J19: =IF(J15,MIN(Equipes!J50,Equipes!J21),"") | ... L19: =IF(L15,MIN(Equipes!L50,Equipes!L21),"")
B20: Horas da equipe/mês | C20: =IF(C15,C19*C18,"") | D20: =IF(D15,D19*D18,"") | E20: =IF(E15,E19*E18,"") | F20: =IF(F15,F19*F18,"") | G20: =IF(G15,G19*G18,"") | H20: =IF(H15,H19*H18,"") | I20: =IF(I15,I19*I18,"") | J20: =IF(J15,J19*J18,"") | ... L20: =IF(L15,L19*L18,"")
B21: Custo do gerente por hora | C21: =IF(C15,C11*Premissas!$C$8/Premissas!$C$9,"") | D21: =IF(D15,D11*Premissas!$C$8/Premissas!$C$9,"") | E21: =IF(E15,E11*Premissas!$C$8/Premissas!$C$9,"") | F21: =IF(F15,F11*Premissas!$C$8/Premissas!$C$9,"") | G21: =IF(G15,G11*Premissas!$C$8/Premissas!$C$9,"") | H21: =IF(H15,H11*Premissas!$C$8/Premissas!$C$9,"") | I21: =IF(I15,I11*Premissas!$C$8/Premissas!$C$9,"") | J21: =IF(J15,J11*Premissas!$C$8/Premissas!$C$9,"") | ... L21: =IF(L15,L11*Premissas!$C$8/Premissas!$C$9,"")
B22: FATORES DE PERFORMANCE | C22: =IF(C15,Equipes!C29/Equipes!C21,"") | D22: =IF(D15,Equipes!D29/Equipes!D21,"") | E22: =IF(E15,Equipes!E29/Equipes!E21,"") | F22: =IF(F15,Equipes!F29/Equipes!F21,"") | G22: =IF(G15,Equipes!G29/Equipes!G21,"") | H22: =IF(H15,Equipes!H29/Equipes!H21,"") | I22: =IF(I15,Equipes!I29/Equipes!I21,"") | J22: =IF(J15,Equipes!J29/Equipes!J21,"") | ... L22: =IF(L15,Equipes!L29/Equipes!L21,"")
B23: Cobertura (assentos/vendedores, máx. 1) | C23: =IF(C15,C10*C9,"") | D23: =IF(D15,D10*D9,"") | E23: =IF(E15,E10*E9,"") | F23: =IF(F15,F10*F9,"") | G23: =IF(G15,G10*G9,"") | H23: =IF(H15,H10*H9,"") | I23: =IF(I15,I10*I9,"") | J23: =IF(J15,J10*J9,"") | ... L23: =IF(L15,L10*L9,"")
B24: Delta ticket efetivo | C24: =IF(C15,Equipes!C24*C9,"") | D24: =IF(D15,Equipes!D24*D9,"") | E24: =IF(E15,Equipes!E24*E9,"") | F24: =IF(F15,Equipes!F24*F9,"") | G24: =IF(G15,Equipes!G24*G9,"") | H24: =IF(H15,Equipes!H24*H9,"") | I24: =IF(I15,Equipes!I24*I9,"") | J24: =IF(J15,Equipes!J24*J9,"") | ... L24: =IF(L15,Equipes!L24*L9,"")
B25: Delta rampa efetivo | C25: =IF(C15,C24*Equipes!C25,"") | D25: =IF(D15,D24*Equipes!D25,"") | E25: =IF(E15,E24*Equipes!E25,"") | F25: =IF(F15,F24*Equipes!F25,"") | G25: =IF(G15,G24*Equipes!G25,"") | H25: =IF(H15,H24*Equipes!H25,"") | I25: =IF(I15,I24*Equipes!I25,"") | J25: =IF(J15,J24*Equipes!J25,"") | ... L25: =IF(L15,L24*Equipes!L25,"")
B27: Delta conversão efetivo (p.p.)
B28: Fator de escopo declarado | C28: =IF(C15,IF(C25>0,C23/C25,""),"") | D28: =IF(D15,IF(D25>0,D23/D25,""),"") | E28: =IF(E15,IF(E25>0,E23/E25,""),"") | F28: =IF(F15,IF(F25>0,F23/F25,""),"") | G28: =IF(G15,IF(G25>0,G23/G25,""),"") | H28: =IF(H15,IF(H25>0,H23/H25,""),"") | I28: =IF(I15,IF(I25>0,I23/I25,""),"") | J28: =IF(J15,IF(J25>0,J23/J25,""),"") | ... L28: =IF(L15,IF(L25>0,L23/L25,""),"")
B29: Fator de escopo fora do intervalo 0,25-6? | C29: =IF(C15,IF(ISNUMBER(C28),OR(C28<Premissas!$C$22,C28>Premissas!$C$23),TRUE()),FALSE()) | D29: =IF(D15,IF(ISNUMBER(D28),OR(D28<Premissas!$C$22,D28>Premissas!$C$23),TRUE()),FALSE()) | E29: =IF(E15,IF(ISNUMBER(E28),OR(E28<Premissas!$C$22,E28>Premissas!$C$23),TRUE()),FALSE()) | F29: =IF(F15,IF(ISNUMBER(F28),OR(F28<Premissas!$C$22,F28>Premissas!$C$23),TRUE()),FALSE()) | G29: =IF(G15,IF(ISNUMBER(G28),OR(G28<Premissas!$C$22,G28>Premissas!$C$23),TRUE()),FALSE()) | H29: =IF(H15,IF(ISNUMBER(H28),OR(H28<Premissas!$C$22,H28>Premissas!$C$23),TRUE()),FALSE()) | I29: =IF(I15,IF(ISNUMBER(I28),OR(I28<Premissas!$C$22,I28>Premissas!$C$23),TRUE()),FALSE()) | J29: =IF(J15,IF(ISNUMBER(J28),OR(J28<Premissas!$C$22,J28>Premissas!$C$23),TRUE()),FALSE()) | ... L29: =IF(L15,IF(ISNUMBER(L28),OR(L28<Premissas!$C$22,L28>Premissas!$C$23),TRUE()),FALSE())
B30: Fator de escopo utilizado | C30: =IF(C15,IF(C29,Premissas!$C$10,C28),"") | D30: =IF(D15,IF(D29,Premissas!$C$10,D28),"") | E30: =IF(E15,IF(E29,Premissas!$C$10,E28),"") | F30: =IF(F15,IF(F29,Premissas!$C$10,F28),"") | G30: =IF(G15,IF(G29,Premissas!$C$10,G28),"") | H30: =IF(H15,IF(H29,Premissas!$C$10,H28),"") | I30: =IF(I15,IF(I29,Premissas!$C$10,I28),"") | J30: =IF(J15,IF(J29,Premissas!$C$10,J28),"") | ... L30: =IF(L15,IF(L29,Premissas!$C$10,L28),"")
B31: Origem do fator | C31: =IF(C15,IF(C29,"premissa (2,1x)","DADOS DO CLIENTE"),"") | D31: =IF(D15,IF(D29,"premissa (2,1x)","DADOS DO CLIENTE"),"") | E31: =IF(E15,IF(E29,"premissa (2,1x)","DADOS DO CLIENTE"),"") | F31: =IF(F15,IF(F29,"premissa (2,1x)","DADOS DO CLIENTE"),"") | G31: =IF(G15,IF(G29,"premissa (2,1x)","DADOS DO CLIENTE"),"") | H31: =IF(H15,IF(H29,"premissa (2,1x)","DADOS DO CLIENTE"),"") | I31: =IF(I15,IF(I29,"premissa (2,1x)","DADOS DO CLIENTE"),"") | J31: =IF(J15,IF(J29,"premissa (2,1x)","DADOS DO CLIENTE"),"") | ... L31: =IF(L15,IF(L29,"premissa (2,1x)","DADOS DO CLIENTE"),"")
B33: COBERTURA E CUSTO MANUAL
B34: Cobertura (assentos/vendedores, máx. 1) | C34: =IF(C15,MIN(1,C19/Equipes!C21),"") | D34: =IF(D15,MIN(1,D19/Equipes!D21),"") | E34: =IF(E15,MIN(1,E19/Equipes!E21),"") | F34: =IF(F15,MIN(1,F19/Equipes!F21),"") | G34: =IF(G15,MIN(1,G19/Equipes!G21),"") | H34: =IF(H15,MIN(1,H19/Equipes!H21),"") | I34: =IF(I15,MIN(1,I19/Equipes!I21),"") | J34: =IF(J15,MIN(1,J19/Equipes!J21),"") | ... L34: =IF(L15,MIN(1,L19/Equipes!L21),"")
B35: Custo manual equivalente/mês | C35: =IF(C15,C20*C21*C30,"") | D35: =IF(D15,D20*D21*D30,"") | E35: =IF(E15,E20*E21*E30,"") | F35: =IF(F15,F20*F21*F30,"") | G35: =IF(G15,G20*G21*G30,"") | H35: =IF(H15,H20*H21*H30,"") | I35: =IF(I15,I20*I21*I30,"") | J35: =IF(J15,J20*J21*J30,"") | ... L35: =IF(L15,L20*L21*L30,"")
B36: Horas economizadas/mês (auto.) | C36: =IF(C15,C20*C30*(1-Premissas!$C$11),"") | D36: =IF(D15,D20*D30*(1-Premissas!$C$11),"") | E36: =IF(E15,E20*E30*(1-Premissas!$C$11),"") | F36: =IF(F15,F20*F30*(1-Premissas!$C$11),"") | G36: =IF(G15,G20*G30*(1-Premissas!$C$11),"") | H36: =IF(H15,H20*H30*(1-Premissas!$C$11),"") | I36: =IF(I15,I20*I30*(1-Premissas!$C$11),"") | J36: =IF(J15,J20*J30*(1-Premissas!$C$11),"") | ... L36: =IF(L15,L20*L30*(1-Premissas!$C$11),"")
B38: Economia de horas/mês
B39: Eficiência (R$/ano) | C39: =IF(C15,C20*C30*C21*(1-Premissas!$C$11)*12,"") | D39: =IF(D15,D20*D30*D21*(1-Premissas!$C$11)*12,"") | E39: =IF(E15,E20*E30*E21*(1-Premissas!$C$11)*12,"") | F39: =IF(F15,F20*F30*F21*(1-Premissas!$C$11)*12,"") | G39: =IF(G15,G20*G30*G21*(1-Premissas!$C$11)*12,"") | H39: =IF(H15,H20*H30*H21*(1-Premissas!$C$11)*12,"") | I39: =IF(I15,I20*I30*I21*(1-Premissas!$C$11)*12,"") | J39: =IF(J15,J20*J30*J21*(1-Premissas!$C$11)*12,"") | ... L39: =IF(L15,L20*L30*L21*(1-Premissas!$C$11)*12,"")
B40: Custo declarado do caminho (ano) | C40: =IF(C15,IF(C12="nenhum",0,IF(C12="gerentes",C10*C9*C21*(1-Premissas!$C$11)*12,IF(C12="treinamento externo",C13*(1-Premissas!$C$11),C14*Premissas!$C$15))),"") | D40: =IF(D15,IF(D12="nenhum",0,IF(D12="gerentes",D10*D9*D21*(1-Premissas!$C$11)*12,IF(D12="treinamento externo",D13*(1-Premissas!$C$11),D14*Premissas!$C$15))),"") | E40: =IF(E15,IF(E12="nenhum",0,IF(E12="gerentes",E10*E9*E21*(1-Premissas!$C$11)*12,IF(E12="treinamento externo",E13*(1-Premissas!$C$11),E14*Premissas!$C$15))),"") | F40: =IF(F15,IF(F12="nenhum",0,IF(F12="gerentes",F10*F9*F21*(1-Premissas!$C$11)*12,IF(F12="treinamento externo",F13*(1-Premissas!$C$11),F14*Premissas!$C$15))),"") | G40: =IF(G15,IF(G12="nenhum",0,IF(G12="gerentes",G10*G9*G21*(1-Premissas!$C$11)*12,IF(G12="treinamento externo",G13*(1-Premissas!$C$11),G14*Premissas!$C$15))),"") | H40: =IF(H15,IF(H12="nenhum",0,IF(H12="gerentes",H10*H9*H21*(1-Premissas!$C$11)*12,IF(H12="treinamento externo",H13*(1-Premissas!$C$11),H14*Premissas!$C$15))),"") | I40: =IF(I15,IF(I12="nenhum",0,IF(I12="gerentes",I10*I9*I21*(1-Premissas!$C$11)*12,IF(I12="treinamento externo",I13*(1-Premissas!$C$11),I14*Premissas!$C$15))),"") | J40: =IF(J15,IF(J12="nenhum",0,IF(J12="gerentes",J10*J9*J21*(1-Premissas!$C$11)*12,IF(J12="treinamento externo",J13*(1-Premissas!$C$11),J14*Premissas!$C$15))),"") | ... L40: =IF(L15,IF(L12="nenhum",0,IF(L12="gerentes",L10*L9*L21*(1-Premissas!$C$11)*12,IF(L12="treinamento externo",L13*(1-Premissas!$C$11),L14*Premissas!$C$15))),"")
B41: Eficiência (R$/ano) | C41: =IF(C15,MIN(C40,C39),"") | D41: =IF(D15,MIN(D40,D39),"") | E41: =IF(E15,MIN(E40,E39),"") | F41: =IF(F15,MIN(F40,F39),"") | G41: =IF(G15,MIN(G40,G39),"") | H41: =IF(H15,MIN(H40,H39),"") | I41: =IF(I15,MIN(I40,I39),"") | J41: =IF(J15,MIN(J40,J39),"") | ... L41: =IF(L15,MIN(L40,L39),"")
B42: Teto de eficiência ativo? | C42: =IF(C15,C40>C39,FALSE()) | D42: =IF(D15,D40>D39,FALSE()) | E42: =IF(E15,E40>E39,FALSE()) | F42: =IF(F15,F40>F39,FALSE()) | G42: =IF(G15,G40>G39,FALSE()) | H42: =IF(H15,H40>H39,FALSE()) | I42: =IF(I15,I40>I39,FALSE()) | J42: =IF(J15,J40>J39,FALSE()) | ... L42: =IF(L15,L40>L39,FALSE())
B44: Receita mensal
B45: Ticket médio | C45: =IF(C15,IF(Equipes!C53="",Premissas!$C$56,MIN(MAX(Equipes!C53,0),Premissas!$C$63)),"") | D45: =IF(D15,IF(Equipes!D53="",Premissas!$C$56,MIN(MAX(Equipes!D53,0),Premissas!$C$63)),"") | E45: =IF(E15,IF(Equipes!E53="",Premissas!$C$56,MIN(MAX(Equipes!E53,0),Premissas!$C$63)),"") | F45: =IF(F15,IF(Equipes!F53="",Premissas!$C$56,MIN(MAX(Equipes!F53,0),Premissas!$C$63)),"") | G45: =IF(G15,IF(Equipes!G53="",Premissas!$C$56,MIN(MAX(Equipes!G53,0),Premissas!$C$63)),"") | H45: =IF(H15,IF(Equipes!H53="",Premissas!$C$56,MIN(MAX(Equipes!H53,0),Premissas!$C$63)),"") | I45: =IF(I15,IF(Equipes!I53="",Premissas!$C$56,MIN(MAX(Equipes!I53,0),Premissas!$C$63)),"") | J45: =IF(J15,IF(Equipes!J53="",Premissas!$C$56,MIN(MAX(Equipes!J53,0),Premissas!$C$63)),"") | ... L45: =IF(L15,IF(Equipes!L53="",Premissas!$C$56,MIN(MAX(Equipes!L53,0),Premissas!$C$63)),"")
B46: Margem | C46: =IF(C15,IF(Equipes!C54="",Premissas!$C$57,MIN(MAX(Equipes!C54,0),Premissas!$C$64)),"") | D46: =IF(D15,IF(Equipes!D54="",Premissas!$C$57,MIN(MAX(Equipes!D54,0),Premissas!$C$64)),"") | E46: =IF(E15,IF(Equipes!E54="",Premissas!$C$57,MIN(MAX(Equipes!E54,0),Premissas!$C$64)),"") | F46: =IF(F15,IF(Equipes!F54="",Premissas!$C$57,MIN(MAX(Equipes!F54,0),Premissas!$C$64)),"") | G46: =IF(G15,IF(Equipes!G54="",Premissas!$C$57,MIN(MAX(Equipes!G54,0),Premissas!$C$64)),"") | H46: =IF(H15,IF(Equipes!H54="",Premissas!$C$57,MIN(MAX(Equipes!H54,0),Premissas!$C$64)),"") | I46: =IF(I15,IF(Equipes!I54="",Premissas!$C$57,MIN(MAX(Equipes!I54,0),Premissas!$C$64)),"") | J46: =IF(J15,IF(Equipes!J54="",Premissas!$C$57,MIN(MAX(Equipes!J54,0),Premissas!$C$64)),"") | ... L46: =IF(L15,IF(Equipes!L54="",Premissas!$C$57,MIN(MAX(Equipes!L54,0),Premissas!$C$64)),"")
B47: Vendas/mês | C47: =IF(C15,MIN(Equipes!C31,1),"") | D47: =IF(D15,MIN(Equipes!D31,1),"") | E47: =IF(E15,MIN(Equipes!E31,1),"") | F47: =IF(F15,MIN(Equipes!F31,1),"") | G47: =IF(G15,MIN(Equipes!G31,1),"") | H47: =IF(H15,MIN(Equipes!H31,1),"") | I47: =IF(I15,MIN(Equipes!I31,1),"") | J47: =IF(J15,MIN(Equipes!J31,1),"") | ... L47: =IF(L15,MIN(Equipes!L31,1),"")
B48: Ganho de ticket/mês | C48: =IF(C15,MAX(0,MIN(5,C47*100*0.4,100-C47*100)),"") | D48: =IF(D15,MAX(0,MIN(5,D47*100*0.4,100-D47*100)),"") | E48: =IF(E15,MAX(0,MIN(5,E47*100*0.4,100-E47*100)),"") | F48: =IF(F15,MAX(0,MIN(5,F47*100*0.4,100-F47*100)),"") | G48: =IF(G15,MAX(0,MIN(5,G47*100*0.4,100-G47*100)),"") | H48: =IF(H15,MAX(0,MIN(5,H47*100*0.4,100-H47*100)),"") | I48: =IF(I15,MAX(0,MIN(5,I47*100*0.4,100-I47*100)),"") | J48: =IF(J15,MAX(0,MIN(5,J47*100*0.4,100-J47*100)),"") | ... L48: =IF(L15,MAX(0,MIN(5,L47*100*0.4,100-L47*100)),"")
B49: Ganho de ticket/ano | C49: =IF(C15,IF(Equipes!C57="",Premissas!$C$59,Equipes!C57),"") | D49: =IF(D15,IF(Equipes!D57="",Premissas!$C$59,Equipes!D57),"") | E49: =IF(E15,IF(Equipes!E57="",Premissas!$C$59,Equipes!E57),"") | F49: =IF(F15,IF(Equipes!F57="",Premissas!$C$59,Equipes!F57),"") | G49: =IF(G15,IF(Equipes!G57="",Premissas!$C$59,Equipes!G57),"") | H49: =IF(H15,IF(Equipes!H57="",Premissas!$C$59,Equipes!H57),"") | I49: =IF(I15,IF(Equipes!I57="",Premissas!$C$59,Equipes!I57),"") | J49: =IF(J15,IF(Equipes!J57="",Premissas!$C$59,Equipes!J57),"") | ... L49: =IF(L15,IF(Equipes!L57="",Premissas!$C$59,Equipes!L57),"")
B50: GANHO DE RAMPA | C50: =IF(C15,MIN(MAX(C49,0),C48),"") | D50: =IF(D15,MIN(MAX(D49,0),D48),"") | E50: =IF(E15,MIN(MAX(E49,0),E48),"") | F50: =IF(F15,MIN(MAX(F49,0),F48),"") | G50: =IF(G15,MIN(MAX(G49,0),G48),"") | H50: =IF(H15,MIN(MAX(H49,0),H48),"") | I50: =IF(I15,MIN(MAX(I49,0),I48),"") | J50: =IF(J15,MIN(MAX(J49,0),J48),"") | ... L50: =IF(L15,MIN(MAX(L49,0),L48),"")
B51: Duração da rampa (meses) | C51: =IF(C15,C47+C50/100,"") | D51: =IF(D15,D47+D50/100,"") | E51: =IF(E15,E47+E50/100,"") | F51: =IF(F15,F47+F50/100,"") | G51: =IF(G15,G47+G50/100,"") | H51: =IF(H15,H47+H50/100,"") | I51: =IF(I15,I47+I50/100,"") | J51: =IF(J15,J47+J50/100,"") | ... L51: =IF(L15,L47+L50/100,"")
B52: Novos vendedores/ano | C52: =IF(N(Equipes!C45)>0,Equipes!C45,"") | D52: =IF(N(Equipes!D45)>0,Equipes!D45,"") | E52: =IF(N(Equipes!E45)>0,Equipes!E45,"") | F52: =IF(N(Equipes!F45)>0,Equipes!F45,"") | G52: =IF(N(Equipes!G45)>0,Equipes!G45,"") | H52: =IF(N(Equipes!H45)>0,Equipes!H45,"") | I52: =IF(N(Equipes!I45)>0,Equipes!I45,"") | J52: =IF(N(Equipes!J45)>0,Equipes!J45,"") | ... L52: =IF(N(Equipes!L45)>0,Equipes!L45,"")
B53: Meses efetivos de rampa | C53: =IF(C15,N(C52)>=7,FALSE()) | D53: =IF(D15,N(D52)>=7,FALSE()) | E53: =IF(E15,N(E52)>=7,FALSE()) | F53: =IF(F15,N(F52)>=7,FALSE()) | G53: =IF(G15,N(G52)>=7,FALSE()) | H53: =IF(H15,N(H52)>=7,FALSE()) | I53: =IF(I15,N(I52)>=7,FALSE()) | J53: =IF(J15,N(J52)>=7,FALSE()) | ... L53: =IF(L15,N(L52)>=7,FALSE())
B54: Ganho de rampa/mês | C54: =IF(C53,ROUND(C52*0.3,0),"") | D54: =IF(D53,ROUND(D52*0.3,0),"") | E54: =IF(E53,ROUND(E52*0.3,0),"") | F54: =IF(F53,ROUND(F52*0.3,0),"") | G54: =IF(G53,ROUND(G52*0.3,0),"") | H54: =IF(H53,ROUND(H52*0.3,0),"") | I54: =IF(I53,ROUND(I52*0.3,0),"") | J54: =IF(J53,ROUND(J52*0.3,0),"") | ... L54: =IF(L53,ROUND(L52*0.3,0),"")
B55: Ganho de rampa/ano | C55: =IF(C53,IF(Equipes!C56="",MAX(1,ROUND(C52*Premissas!$C$58,0)),MIN(MAX(ROUND(Equipes!C56,0),0),C54)),"") | D55: =IF(D53,IF(Equipes!D56="",MAX(1,ROUND(D52*Premissas!$C$58,0)),MIN(MAX(ROUND(Equipes!D56,0),0),D54)),"") | E55: =IF(E53,IF(Equipes!E56="",MAX(1,ROUND(E52*Premissas!$C$58,0)),MIN(MAX(ROUND(Equipes!E56,0),0),E54)),"") | F55: =IF(F53,IF(Equipes!F56="",MAX(1,ROUND(F52*Premissas!$C$58,0)),MIN(MAX(ROUND(Equipes!F56,0),0),F54)),"") | G55: =IF(G53,IF(Equipes!G56="",MAX(1,ROUND(G52*Premissas!$C$58,0)),MIN(MAX(ROUND(Equipes!G56,0),0),G54)),"") | H55: =IF(H53,IF(Equipes!H56="",MAX(1,ROUND(H52*Premissas!$C$58,0)),MIN(MAX(ROUND(Equipes!H56,0),0),H54)),"") | I55: =IF(I53,IF(Equipes!I56="",MAX(1,ROUND(I52*Premissas!$C$58,0)),MIN(MAX(ROUND(Equipes!I56,0),0),I54)),"") | J55: =IF(J53,IF(Equipes!J56="",MAX(1,ROUND(J52*Premissas!$C$58,0)),MIN(MAX(ROUND(Equipes!J56,0),0),J54)),"") | ... L55: =IF(L53,IF(Equipes!L56="",MAX(1,ROUND(L52*Premissas!$C$58,0)),MIN(MAX(ROUND(Equipes!L56,0),0),L54)),"")
B56: GANHO DE CONVERSÃO | C56: =IF(C15,IF(C53,C55/C52,MIN(MAX(IF(Equipes!C55="",Premissas!$C$58,Equipes!C55),0),Premissas!$C$65)),"") | D56: =IF(D15,IF(D53,D55/D52,MIN(MAX(IF(Equipes!D55="",Premissas!$C$58,Equipes!D55),0),Premissas!$C$65)),"") | E56: =IF(E15,IF(E53,E55/E52,MIN(MAX(IF(Equipes!E55="",Premissas!$C$58,Equipes!E55),0),Premissas!$C$65)),"") | F56: =IF(F15,IF(F53,F55/F52,MIN(MAX(IF(Equipes!F55="",Premissas!$C$58,Equipes!F55),0),Premissas!$C$65)),"") | G56: =IF(G15,IF(G53,G55/G52,MIN(MAX(IF(Equipes!G55="",Premissas!$C$58,Equipes!G55),0),Premissas!$C$65)),"") | H56: =IF(H15,IF(H53,H55/H52,MIN(MAX(IF(Equipes!H55="",Premissas!$C$58,Equipes!H55),0),Premissas!$C$65)),"") | I56: =IF(I15,IF(I53,I55/I52,MIN(MAX(IF(Equipes!I55="",Premissas!$C$58,Equipes!I55),0),Premissas!$C$65)),"") | J56: =IF(J15,IF(J53,J55/J52,MIN(MAX(IF(Equipes!J55="",Premissas!$C$58,Equipes!J55),0),Premissas!$C$65)),"") | ... L56: =IF(L15,IF(L53,L55/L52,MIN(MAX(IF(Equipes!L55="",Premissas!$C$58,Equipes!L55),0),Premissas!$C$65)),"")
B57: Receita / ticket = oportunidades convertidas/mês | C57: =IF(C53,C52-C55,"") | D57: =IF(D53,D52-D55,"") | E57: =IF(E53,E52-E55,"") | F57: =IF(F53,F52-F55,"") | G57: =IF(G53,G52-G55,"") | H57: =IF(H53,H52-H55,"") | I57: =IF(I53,I52-I55,"") | J57: =IF(J53,J52-J55,"") | ... L57: =IF(L53,L52-L55,"")
B59: Conversão atual
B60: Ganho de ticket via conversão/ano | C60: =IF(C15,Equipes!C29*C45*12*Equipes!C32*C34,"") | D60: =IF(D15,Equipes!D29*D45*12*Equipes!D32*D34,"") | E60: =IF(E15,Equipes!E29*E45*12*Equipes!E32*E34,"") | F60: =IF(F15,Equipes!F29*F45*12*Equipes!F32*F34,"") | G60: =IF(G15,Equipes!G29*G45*12*Equipes!G32*G34,"") | H60: =IF(H15,Equipes!H29*H45*12*Equipes!H32*H34,"") | I60: =IF(I15,Equipes!I29*I45*12*Equipes!I32*I34,"") | J60: =IF(J15,Equipes!J29*J45*12*Equipes!J32*J34,"") | ... L60: =IF(L15,Equipes!L29*L45*12*Equipes!L32*L34,"")
B61: Margem de rampa via conversão/ano | C61: =IF(C15,Equipes!C35*C46*C22*Equipes!C36*Equipes!C32*Premissas!$C$12*C34,"") | D61: =IF(D15,Equipes!D35*D46*D22*Equipes!D36*Equipes!D32*Premissas!$C$12*D34,"") | E61: =IF(E15,Equipes!E35*E46*E22*Equipes!E36*Equipes!E32*Premissas!$C$12*E34,"") | F61: =IF(F15,Equipes!F35*F46*F22*Equipes!F36*Equipes!F32*Premissas!$C$12*F34,"") | G61: =IF(G15,Equipes!G35*G46*G22*Equipes!G36*Equipes!G32*Premissas!$C$12*G34,"") | H61: =IF(H15,Equipes!H35*H46*H22*Equipes!H36*Equipes!H32*Premissas!$C$12*H34,"") | I61: =IF(I15,Equipes!I35*I46*I22*Equipes!I36*Equipes!I32*Premissas!$C$12*I34,"") | J61: =IF(J15,Equipes!J35*J46*J22*Equipes!J36*Equipes!J32*Premissas!$C$12*J34,"") | ... L61: =IF(L15,Equipes!L35*L46*L22*Equipes!L36*Equipes!L32*Premissas!$C$12*L34,"")
B62: Ganho de conversão/ano | C62: =IF(C15,(Equipes!C29/Equipes!C30)/C47*C50/100*Equipes!C30*Equipes!C32*12*Premissas!$C$14*C34,"") | D62: =IF(D15,(Equipes!D29/Equipes!D30)/D47*D50/100*Equipes!D30*Equipes!D32*12*Premissas!$C$14*D34,"") | E62: =IF(E15,(Equipes!E29/Equipes!E30)/E47*E50/100*Equipes!E30*Equipes!E32*12*Premissas!$C$14*E34,"") | F62: =IF(F15,(Equipes!F29/Equipes!F30)/F47*F50/100*Equipes!F30*Equipes!F32*12*Premissas!$C$14*F34,"") | G62: =IF(G15,(Equipes!G29/Equipes!G30)/G47*G50/100*Equipes!G30*Equipes!G32*12*Premissas!$C$14*G34,"") | H62: =IF(H15,(Equipes!H29/Equipes!H30)/H47*H50/100*Equipes!H30*Equipes!H32*12*Premissas!$C$14*H34,"") | I62: =IF(I15,(Equipes!I29/Equipes!I30)/I47*I50/100*Equipes!I30*Equipes!I32*12*Premissas!$C$14*I34,"") | J62: =IF(J15,(Equipes!J29/Equipes!J30)/J47*J50/100*Equipes!J30*Equipes!J32*12*Premissas!$C$14*J34,"") | ... L62: =IF(L15,(Equipes!L29/Equipes!L30)/L47*L50/100*Equipes!L30*Equipes!L32*12*Premissas!$C$14*L34,"")
B63: GANHO DE CICLO | C63: =IF(C15,AND(N(C52)>0,N(Equipes!C46)>0),FALSE()) | D63: =IF(D15,AND(N(D52)>0,N(Equipes!D46)>0),FALSE()) | E63: =IF(E15,AND(N(E52)>0,N(Equipes!E46)>0),FALSE()) | F63: =IF(F15,AND(N(F52)>0,N(Equipes!F46)>0),FALSE()) | G63: =IF(G15,AND(N(G52)>0,N(Equipes!G46)>0),FALSE()) | H63: =IF(H15,AND(N(H52)>0,N(Equipes!H46)>0),FALSE()) | I63: =IF(I15,AND(N(I52)>0,N(Equipes!I46)>0),FALSE()) | J63: =IF(J15,AND(N(J52)>0,N(Equipes!J46)>0),FALSE()) | ... L63: =IF(L15,AND(N(L52)>0,N(Equipes!L46)>0),FALSE())
B64: Ciclo de vendas (dias) | C64: =IF(C63,MAX(0,Equipes!C46-(Equipes!C29/Equipes!C30)/C47),"") | D64: =IF(D63,MAX(0,Equipes!D46-(Equipes!D29/Equipes!D30)/D47),"") | E64: =IF(E63,MAX(0,Equipes!E46-(Equipes!E29/Equipes!E30)/E47),"") | F64: =IF(F63,MAX(0,Equipes!F46-(Equipes!F29/Equipes!F30)/F47),"") | G64: =IF(G63,MAX(0,Equipes!G46-(Equipes!G29/Equipes!G30)/G47),"") | H64: =IF(H63,MAX(0,Equipes!H46-(Equipes!H29/Equipes!H30)/H47),"") | I64: =IF(I63,MAX(0,Equipes!I46-(Equipes!I29/Equipes!I30)/I47),"") | J64: =IF(J63,MAX(0,Equipes!J46-(Equipes!J29/Equipes!J30)/J47),"") | ... L64: =IF(L63,MAX(0,Equipes!L46-(Equipes!L29/Equipes!L30)/L47),"")
B65: Oportunidades/mês | C65: =IF(C63,C64*C47,"") | D65: =IF(D63,D64*D47,"") | E65: =IF(E63,E64*E47,"") | F65: =IF(F63,F64*F47,"") | G65: =IF(G63,G64*G47,"") | H65: =IF(H63,H64*H47,"") | I65: =IF(I63,I64*I47,"") | J65: =IF(J63,J64*J47,"") | ... L65: =IF(L63,L64*L47,"")
B66: Meses p/ processar 1 oportunidade | C66: =IF(C63,IF(AND(C56>0,C56<1),(Equipes!C29/Equipes!C30)*(1/(1-C56)-1),0),"") | D66: =IF(D63,IF(AND(D56>0,D56<1),(Equipes!D29/Equipes!D30)*(1/(1-D56)-1),0),"") | E66: =IF(E63,IF(AND(E56>0,E56<1),(Equipes!E29/Equipes!E30)*(1/(1-E56)-1),0),"") | F66: =IF(F63,IF(AND(F56>0,F56<1),(Equipes!F29/Equipes!F30)*(1/(1-F56)-1),0),"") | G66: =IF(G63,IF(AND(G56>0,G56<1),(Equipes!G29/Equipes!G30)*(1/(1-G56)-1),0),"") | H66: =IF(H63,IF(AND(H56>0,H56<1),(Equipes!H29/Equipes!H30)*(1/(1-H56)-1),0),"") | I66: =IF(I63,IF(AND(I56>0,I56<1),(Equipes!I29/Equipes!I30)*(1/(1-I56)-1),0),"") | J66: =IF(J63,IF(AND(J56>0,J56<1),(Equipes!J29/Equipes!J30)*(1/(1-J56)-1),0),"") | ... L66: =IF(L63,IF(AND(L56>0,L56<1),(Equipes!L29/Equipes!L30)*(1/(1-L56)-1),0),"")
B67: Ganho de ciclo/mês | C67: =IF(C63,MIN(C66,C65),"") | D67: =IF(D63,MIN(D66,D65),"") | E67: =IF(E63,MIN(E66,E65),"") | F67: =IF(F63,MIN(F66,F65),"") | G67: =IF(G63,MIN(G66,G65),"") | H67: =IF(H63,MIN(H66,H65),"") | I67: =IF(I63,MIN(I66,I65),"") | J67: =IF(J63,MIN(J66,J65),"") | ... L67: =IF(L63,MIN(L66,L65),"")
B68: Ganho de ciclo/ano | C68: =IF(C15,IF(C63,C67*Equipes!C30*Equipes!C32*12*Premissas!$C$13*C34,0),"") | D68: =IF(D15,IF(D63,D67*Equipes!D30*Equipes!D32*12*Premissas!$C$13*D34,0),"") | E68: =IF(E15,IF(E63,E67*Equipes!E30*Equipes!E32*12*Premissas!$C$13*E34,0),"") | F68: =IF(F15,IF(F63,F67*Equipes!F30*Equipes!F32*12*Premissas!$C$13*F34,0),"") | G68: =IF(G15,IF(G63,G67*Equipes!G30*Equipes!G32*12*Premissas!$C$13*G34,0),"") | H68: =IF(H15,IF(H63,H67*Equipes!H30*Equipes!H32*12*Premissas!$C$13*H34,0),"") | I68: =IF(I15,IF(I63,I67*Equipes!I30*Equipes!I32*12*Premissas!$C$13*I34,0),"") | J68: =IF(J15,IF(J63,J67*Equipes!J30*Equipes!J32*12*Premissas!$C$13*J34,0),"") | ... L68: =IF(L15,IF(L63,L67*Equipes!L30*Equipes!L32*12*Premissas!$C$13*L34,0),"")
B69: Teto do funil limitante? | C69: =IF(C63,OR(C67<C66,C64=0),FALSE()) | D69: =IF(D63,OR(D67<D66,D64=0),FALSE()) | E69: =IF(E63,OR(E67<E66,E64=0),FALSE()) | F69: =IF(F63,OR(F67<F66,F64=0),FALSE()) | G69: =IF(G63,OR(G67<G66,G64=0),FALSE()) | H69: =IF(H63,OR(H67<H66,H64=0),FALSE()) | I69: =IF(I63,OR(I67<I66,I64=0),FALSE()) | J69: =IF(J63,OR(J67<J66,J64=0),FALSE()) | ... L69: =IF(L63,OR(L67<L66,L64=0),FALSE())
B71: Valor anual total da equipe
B72: Margem atual da equipe (ano) | C72: =IF(C15,C41+C60+C61+C62+C68,"") | D72: =IF(D15,D41+D60+D61+D62+D68,"") | E72: =IF(E15,E41+E60+E61+E62+E68,"") | F72: =IF(F15,F41+F60+F61+F62+F68,"") | G72: =IF(G15,G41+G60+G61+G62+G68,"") | H72: =IF(H15,H41+H60+H61+H62+H68,"") | I72: =IF(I15,I41+I60+I61+I62+I68,"") | J72: =IF(J15,J41+J60+J61+J62+J68,"") | ... L72: =IF(L15,L41+L60+L61+L62+L68,"")
B73: ROI da equipe | C73: =IF(C15,C60+C61+C62+C68,"") | D73: =IF(D15,D60+D61+D62+D68,"") | E73: =IF(E15,E60+E61+E62+E68,"") | F73: =IF(F15,F60+F61+F62+F68,"") | G73: =IF(G15,G60+G61+G62+G68,"") | H73: =IF(H15,H60+H61+H62+H68,"") | I73: =IF(I15,I60+I61+I62+I68,"") | J73: =IF(J15,J60+J61+J62+J68,"") | ... L73: =IF(L15,L60+L61+L62+L68,"")
B74: Payback da equipe (meses) | C74: =IF(C15,Equipes!C29*12*Equipes!C32,"") | D74: =IF(D15,Equipes!D29*12*Equipes!D32,"") | E74: =IF(E15,Equipes!E29*12*Equipes!E32,"") | F74: =IF(F15,Equipes!F29*12*Equipes!F32,"") | G74: =IF(G15,Equipes!G29*12*Equipes!G32,"") | H74: =IF(H15,Equipes!H29*12*Equipes!H32,"") | I74: =IF(I15,Equipes!I29*12*Equipes!I32,"") | J74: =IF(J15,Equipes!J29*12*Equipes!J32,"") | ... L74: =IF(L15,Equipes!L29*12*Equipes!L32,"")
B75: Teste de realismo (G / margem anual) | C75: =IF(C15,C73/C74,"") | D75: =IF(D15,D73/D74,"") | E75: =IF(E15,E73/E74,"") | F75: =IF(F15,F73/F74,"") | G75: =IF(G15,G73/G74,"") | H75: =IF(H15,H73/H74,"") | I75: =IF(I15,I73/I74,"") | J75: =IF(J15,J73/J74,"") | ... L75: =IF(L15,L73/L74,"")
B76: Alerta teste de realismo (> 25%)? | C76: =IF(C15,N(C75)>Premissas!$C$26,FALSE()) | D76: =IF(D15,N(D75)>Premissas!$C$26,FALSE()) | E76: =IF(E15,N(E75)>Premissas!$C$26,FALSE()) | F76: =IF(F15,N(F75)>Premissas!$C$26,FALSE()) | G76: =IF(G15,N(G75)>Premissas!$C$26,FALSE()) | H76: =IF(H15,N(H75)>Premissas!$C$26,FALSE()) | I76: =IF(I15,N(I75)>Premissas!$C$26,FALSE()) | J76: =IF(J15,N(J75)>Premissas!$C$26,FALSE()) | ... L76: =IF(L15,N(L75)>Premissas!$C$26,FALSE())
B78: PREÇO POR EQUIPE (da aba Conta)
B79: Preço mensal (alocado por horas) | C79: =IF(AND(C15,N(Conta!$C$13)>0,ISNUMBER(Conta!$C$22)),Conta!$C$22*C20/Conta!$C$13,"") | D79: =IF(AND(D15,N(Conta!$C$13)>0,ISNUMBER(Conta!$C$22)),Conta!$C$22*D20/Conta!$C$13,"") | E79: =IF(AND(E15,N(Conta!$C$13)>0,ISNUMBER(Conta!$C$22)),Conta!$C$22*E20/Conta!$C$13,"") | F79: =IF(AND(F15,N(Conta!$C$13)>0,ISNUMBER(Conta!$C$22)),Conta!$C$22*F20/Conta!$C$13,"") | G79: =IF(AND(G15,N(Conta!$C$13)>0,ISNUMBER(Conta!$C$22)),Conta!$C$22*G20/Conta!$C$13,"") | H79: =IF(AND(H15,N(Conta!$C$13)>0,ISNUMBER(Conta!$C$22)),Conta!$C$22*H20/Conta!$C$13,"") | I79: =IF(AND(I15,N(Conta!$C$13)>0,ISNUMBER(Conta!$C$22)),Conta!$C$22*I20/Conta!$C$13,"") | J79: =IF(AND(J15,N(Conta!$C$13)>0,ISNUMBER(Conta!$C$22)),Conta!$C$22*J20/Conta!$C$13,"") | ... L79: =IF(AND(L15,N(Conta!$C$13)>0,ISNUMBER(Conta!$C$22)),Conta!$C$22*L20/Conta!$C$13,"")
B80: Preço anual | C80: =IF(ISNUMBER(C79),C79*12,"") | D80: =IF(ISNUMBER(D79),D79*12,"") | E80: =IF(ISNUMBER(E79),E79*12,"") | F80: =IF(ISNUMBER(F79),F79*12,"") | G80: =IF(ISNUMBER(G79),G79*12,"") | H80: =IF(ISNUMBER(H79),H79*12,"") | I80: =IF(ISNUMBER(I79),I79*12,"") | J80: =IF(ISNUMBER(J79),J79*12,"") | ... L80: =IF(ISNUMBER(L79),L79*12,"")
B81: ROI da equipe | C81: =IF(AND(ISNUMBER(C80),N(C80)>0,ISNUMBER(C72)),C72/C80,"") | D81: =IF(AND(ISNUMBER(D80),N(D80)>0,ISNUMBER(D72)),D72/D80,"") | E81: =IF(AND(ISNUMBER(E80),N(E80)>0,ISNUMBER(E72)),E72/E80,"") | F81: =IF(AND(ISNUMBER(F80),N(F80)>0,ISNUMBER(F72)),F72/F80,"") | G81: =IF(AND(ISNUMBER(G80),N(G80)>0,ISNUMBER(G72)),G72/G80,"") | H81: =IF(AND(ISNUMBER(H80),N(H80)>0,ISNUMBER(H72)),H72/H80,"") | I81: =IF(AND(ISNUMBER(I80),N(I80)>0,ISNUMBER(I72)),I72/I80,"") | J81: =IF(AND(ISNUMBER(J80),N(J80)>0,ISNUMBER(J72)),J72/J80,"") | ... L81: =IF(AND(ISNUMBER(L80),N(L80)>0,ISNUMBER(L72)),L72/L80,"")
B82: Payback da equipe (meses) | C82: =IF(AND(ISNUMBER(C81),N(C72)>0),C80/C72*12,"") | D82: =IF(AND(ISNUMBER(D81),N(D72)>0),D80/D72*12,"") | E82: =IF(AND(ISNUMBER(E81),N(E72)>0),E80/E72*12,"") | F82: =IF(AND(ISNUMBER(F81),N(F72)>0),F80/F72*12,"") | G82: =IF(AND(ISNUMBER(G81),N(G72)>0),G80/G72*12,"") | H82: =IF(AND(ISNUMBER(H81),N(H72)>0),H80/H72*12,"") | I82: =IF(AND(ISNUMBER(I81),N(I72)>0),I80/I72*12,"") | J82: =IF(AND(ISNUMBER(J81),N(J72)>0),J80/J72*12,"") | ... L82: =IF(AND(ISNUMBER(L81),N(L72)>0),L80/L72*12,"")
B83: Payback excede o contrato? | C83: =IF(ISNUMBER(C82),C82>Conta!$C$8,FALSE()) | D83: =IF(ISNUMBER(D82),D82>Conta!$C$8,FALSE()) | E83: =IF(ISNUMBER(E82),E82>Conta!$C$8,FALSE()) | F83: =IF(ISNUMBER(F82),F82>Conta!$C$8,FALSE()) | G83: =IF(ISNUMBER(G82),G82>Conta!$C$8,FALSE()) | H83: =IF(ISNUMBER(H82),H82>Conta!$C$8,FALSE()) | I83: =IF(ISNUMBER(I82),I82>Conta!$C$8,FALSE()) | J83: =IF(ISNUMBER(J82),J82>Conta!$C$8,FALSE()) | ... L83: =IF(ISNUMBER(L82),L82>Conta!$C$8,FALSE())
B84: Preço por assento (mês) | C84: =IF(ISNUMBER(C79),C79/C19,"") | D84: =IF(ISNUMBER(D79),D79/D19,"") | E84: =IF(ISNUMBER(E79),E79/E19,"") | F84: =IF(ISNUMBER(F79),F79/F19,"") | G84: =IF(ISNUMBER(G79),G79/G19,"") | H84: =IF(ISNUMBER(H79),H79/H19,"") | I84: =IF(ISNUMBER(I79),I79/I19,"") | J84: =IF(ISNUMBER(J79),J79/J19,"") | ... L84: =IF(ISNUMBER(L79),L79/L19,"")
B85: Valor por vendedor/ano | C85: =IF(C15,C72/Equipes!C21,"") | D85: =IF(D15,D72/Equipes!D21,"") | E85: =IF(E15,E72/Equipes!E21,"") | F85: =IF(F15,F72/Equipes!F21,"") | G85: =IF(G15,G72/Equipes!G21,"") | H85: =IF(H15,H72/Equipes!H21,"") | I85: =IF(I15,I72/Equipes!I21,"") | J85: =IF(J15,J72/Equipes!J21,"") | ... L85: =IF(L15,L72/Equipes!L21,"")
B87: ECONOMIA DE HEADCOUNT (referência — excluído do valor por auditoria A-02)
B88: Gerentes necessários hoje | C88: =IF(C15,Equipes!C21/Equipes!C24,"") | D88: =IF(D15,Equipes!D21/Equipes!D24,"") | E88: =IF(E15,Equipes!E21/Equipes!E24,"") | F88: =IF(F15,Equipes!F21/Equipes!F24,"") | G88: =IF(G15,Equipes!G21/Equipes!G24,"") | H88: =IF(H15,Equipes!H21/Equipes!H24,"") | I88: =IF(I15,Equipes!I21/Equipes!I24,"") | J88: =IF(J15,Equipes!J21/Equipes!J24,"") | ... L88: =IF(L15,Equipes!L21/Equipes!L24,"")
B89: Gerentes necessários com Perfecting | C89: =IF(C15,IF(Premissas!$C$11>0,Equipes!C21/(Equipes!C24*(1/Premissas!$C$11)),""),"") | D89: =IF(D15,IF(Premissas!$C$11>0,Equipes!D21/(Equipes!D24*(1/Premissas!$C$11)),""),"") | E89: =IF(E15,IF(Premissas!$C$11>0,Equipes!E21/(Equipes!E24*(1/Premissas!$C$11)),""),"") | F89: =IF(F15,IF(Premissas!$C$11>0,Equipes!F21/(Equipes!F24*(1/Premissas!$C$11)),""),"") | G89: =IF(G15,IF(Premissas!$C$11>0,Equipes!G21/(Equipes!G24*(1/Premissas!$C$11)),""),"") | H89: =IF(H15,IF(Premissas!$C$11>0,Equipes!H21/(Equipes!H24*(1/Premissas!$C$11)),""),"") | I89: =IF(I15,IF(Premissas!$C$11>0,Equipes!I21/(Equipes!I24*(1/Premissas!$C$11)),""),"") | J89: =IF(J15,IF(Premissas!$C$11>0,Equipes!J21/(Equipes!J24*(1/Premissas!$C$11)),""),"") | ... L89: =IF(L15,IF(Premissas!$C$11>0,Equipes!L21/(Equipes!L24*(1/Premissas!$C$11)),""),"")
B90: Gerentes evitados | C90: =IF(C15,IF(ISNUMBER(C89),MAX(0,C88-C89),""),"") | D90: =IF(D15,IF(ISNUMBER(D89),MAX(0,D88-D89),""),"") | E90: =IF(E15,IF(ISNUMBER(E89),MAX(0,E88-E89),""),"") | F90: =IF(F15,IF(ISNUMBER(F89),MAX(0,F88-F89),""),"") | G90: =IF(G15,IF(ISNUMBER(G89),MAX(0,G88-G89),""),"") | H90: =IF(H15,IF(ISNUMBER(H89),MAX(0,H88-H89),""),"") | I90: =IF(I15,IF(ISNUMBER(I89),MAX(0,I88-I89),""),"") | J90: =IF(J15,IF(ISNUMBER(J89),MAX(0,J88-J89),""),"") | ... L90: =IF(L15,IF(ISNUMBER(L89),MAX(0,L88-L89),""),"")
B91: Economia de headcount (ano) | C91: =IF(AND(C15,ISNUMBER(C90)),C90*C11*Premissas!$C$8*12,"") | D91: =IF(AND(D15,ISNUMBER(D90)),D90*D11*Premissas!$C$8*12,"") | E91: =IF(AND(E15,ISNUMBER(E90)),E90*E11*Premissas!$C$8*12,"") | F91: =IF(AND(F15,ISNUMBER(F90)),F90*F11*Premissas!$C$8*12,"") | G91: =IF(AND(G15,ISNUMBER(G90)),G90*G11*Premissas!$C$8*12,"") | H91: =IF(AND(H15,ISNUMBER(H90)),H90*H11*Premissas!$C$8*12,"") | I91: =IF(AND(I15,ISNUMBER(I90)),I90*I11*Premissas!$C$8*12,"") | J91: =IF(AND(J15,ISNUMBER(J90)),J90*J11*Premissas!$C$8*12,"") | ... L91: =IF(AND(L15,ISNUMBER(L90)),L90*L11*Premissas!$C$8*12,"")

Sheet Custo da Inação
B1: Custo da Inação (COI)
B2: Quanto custa NÃO investir em coaching contínuo para vendas | Baseado em pesquisa MySalesCoach 2026, Ebsta, Gartner, Dixon/McKenna HBR
B3: Este módulo expõe o GAP entre o coaching que acontece e o que deveria acontecer. Aditivo ao ROI — cria urgência antes da justificativa de investimento.
B6: DIMENSÃO 1 — GAP DE COBERTURA DE COACHING
B7: Parâmetro | C7: Valor | D7: Unidade | E7: Fonte / Observação
B8: Total de vendedores | C8: =IF(N(Conta!C43)>0,Conta!C43,0) | D8: vendedores | E8: Cross-reference da aba Conta
B9: Vendedores cobertos/mês (hoje) | C9: =IF(N(Motor!C23)>0,Motor!C23*Motor!C9,IF(N(Equipes!C24)>0,Equipes!C24*Motor!C9,N(Conta!C43)*0.28)) | D9: vendedores | E9: Só 28% recebem coaching semanal (MySalesCoach 2026). Fórmula: cobertos × horas_train
B10: Gap de cobertura de coaching | C10: =IF(AND(ISNUMBER(C8),C8>0),IF(ISNUMBER(C9),(C8-C9)/C8,1-0.28),) | D10: % | E10: Gap = (total - cobertos) / total. Se 100 vendedores e 28 cobertos → 72% gap
B11: Vendedores NÃO treinados/mês | C11: =IF(ISNUMBER(C8),IF(ISNUMBER(C9),C8-C9,C8*(1-0.28)),) | D11: vendedores | E11: Vendedores sem coaching regular
B13: DIMENSÃO 2 — PERDA DE RECEITA POR SUB-PERFORMANCE
B14: Parâmetro | C14: Valor | D14: Unidade | E14: Fonte / Observação
B15: Delta de atingimento de quota (quota attainment, semanal vs trimestral) | C15: 0.29 | D15: p.p. | E15: MySalesCoach 2026: 76% (semanal) vs 47% (trimestral) = 29pp gap. 3.700+ profissionais
B16: Haircut COI (conservador) | C16: 0.5 | E16: Desconto anti-otimismo: aplica 50% do delta. Mesma lógica dos haircuts do Motor
B17: Delta efetivo de attainment | C17: =C15*C16 | D17: p.p. | E17: Delta aplicado com haircut
B18: Receita média/vendedor/mês | C18: =IF(AND(ISNUMBER(Equipes!C29),Conta!C43>0),Equipes!C29/Conta!C43,) | D18: R$/mês | E18: Receita da equipe / total vendedores (cross-ref Equipes + Conta)
B19: Receita perdida/vendedor não treinado/mês | C19: =IF(AND(ISNUMBER(C18),ISNUMBER(C17)),C18*C17,) | D19: R$/mês | E19: receita_média × delta_efetivo (decimal)
B20: Receita perdida total/mês | C20: =IF(AND(ISNUMBER(C19),ISNUMBER(C11)),C19*C11,) | D20: R$/mês | E20: receita_perdida × vendedores_não_treinados
B21: COI Receita Anual | C21: =IF(ISNUMBER(C20),C20*12,) | D21: R$/ano | E21: Custo da inação em receita por sub-performance
B23: DIMENSÃO 3 — CUSTO DE RAMPA ESTENDIDA
B24: Parâmetro | C24: Valor | D24: Unidade | E24: Fonte / Observação
B25: Rampa média atual | C25: =IF(ISNUMBER(Equipes!C35),Equipes!C35,5.3) | D25: meses | E25: Dado do cliente ou benchmark: 5,3 meses (CareerTrainer.ai 2026)
B26: Extensão por falta de coaching | C26: 1.4 | D26: meses | E26: Ebsta 2024: rampa aumentou de 4,3 para 5,7 meses (1,4 meses adicionais)
B27: Haircut rampa COI | C27: 0.5 | E27: Desconto conservador: aplica 50% da extensão
B28: Meses adicionais efetivos | C28: =C26*C27 | D28: meses | E28: extensão × haircut
B29: Novos vendedores/ano | C29: =IF(ISNUMBER(Equipes!C36),Equipes!C36,N(Conta!C43)*0.2) | D29: vendedores | E29: Dado do cliente ou estimativa: ~20% turnover/ano
B30: Receita perdida/mês por vendedor em rampa | C30: =IF(ISNUMBER(C18),C18*0.5,) | D30: R$/mês | E30: Vendedor em rampa gera ~50% da receita plena (conservador)
B31: COI Rampa Anual | C31: =IF(AND(ISNUMBER(C28),ISNUMBER(C29),ISNUMBER(C30)),C28*C29*C30,) | D31: R$/ano | E31: meses_adicionais × novos_ano × receita_perdida_rampa
B33: DIMENSÃO 4 — CUSTO DE TURNOVER POR FALTA DE COACHING
B34: Parâmetro | C34: Valor | D34: Unidade | E34: Fonte / Observação
B35: Taxa de retenção com coaching frequente | C35: 0.74 | D35: % | E35: MySalesCoach 2026: 74% dos SDRs com coaching esperam ficar 12 meses
B36: Taxa de retenção sem coaching | C36: 0.34 | D36: % | E36: MySalesCoach 2026: apenas 34% sem coaching esperam ficar. Gap de 40pp
B37: Delta de attrition | C37: =C35-C36 | D37: p.p. | E37: Diferença de retenção entre com e sem coaching
B38: Taxa de turnover adicional | C38: =IF(ISNUMBER(C37),C37,) | D38: % | E38: Proporção extra de vendedores que saem por falta de coaching
B39: Salário mensal do vendedor | C39: =IF(ISNUMBER(Equipes!C37),Equipes!C37,0) | D39: R$/mês | E39: Dado do cliente (aba Equipes)
B40: Custo de substituição (multiplicador) | C40: 1 | D40: × salário | E40: Range: 50-150% do salário anual (SHRM/Gallup). 1× = conservador
B41: Custo por turnover | C41: =IF(AND(ISNUMBER(C39),ISNUMBER(C40)),C39*Premissas!C8*C40*12,) | D41: R$/pessoa | E41: salário × encargos × multiplicador × 12
B42: COI Turnover Anual | C42: =IF(AND(ISNUMBER(C38),ISNUMBER(C8),ISNUMBER(C41)),C38*C8*C41,) | D42: R$/ano | E42: turnover_adicional × vendedores_total × custo_por_turnover
B44: DIMENSÃO 5 — IMPOSTO DO APRENDIZADO EM VIVO (LIVE-LEARNING TAX)
B45: Parâmetro | C45: Valor | D45: Unidade | E45: Fonte / Observação
B46: Taxa de negócios perdidos por "sem decisão" (no decision / status quo) | C46: 0.5 | D46: % | E46: Dixon & McKenna HBR: 40-60% dos deals B2B perdidos para "no decision". 50% = ponto médio
B47: Fração de "no decisions" atribuíveis a falta de coaching | C47: 0.2 | D47: % | E47: Conservador: 20% dos negócios em status quo seriam ganhos com coaching de descoberta (discovery)
B48: Ticket médio | C48: =IF(ISNUMBER(Equipes!C30),Equipes!C30,0) | D48: R$ | E48: Cross-reference da aba Equipes
B49: Deals ganhos adicionalmente/mês | C49: =IF(AND(ISNUMBER(C18),ISNUMBER(C8),ISNUMBER(C48),ISNUMBER(C46),ISNUMBER(C47)),(C18*C8/C48)*C46*C47,) | D49: deals/mês | E49: (receita_total/ticket) × taxa_no_decision × fração_coachável
B50: COI Live-Learning Anual | C50: =IF(AND(ISNUMBER(C49),ISNUMBER(C48)),C49*C48*12,) | D50: R$/ano | E50: deals_adicionais × ticket × 12
B52: DIMENSÃO 6 — CUSTO DA FILA DE ESPERA POR COACHING
B53: Parâmetro | C53: Valor | D53: Unidade | E53: Fonte / Observação
B54: Vendedores na fila de espera por coaching | C54: =IF(ISNUMBER(C11),C11,0) | D54: vendedores | E54: Mesmos vendedores não treinados (Dimensão 1). Aguardam vaga na agenda do gerente
B55: Semanas médias de espera | C55: 2 | D55: semanas | E55: Conservador: 2 semanas até conseguir 1h de coaching. Em ops grandes pode ser 4+
B56: Horas produtivas perdidas/vendedor/semana de espera | C56: 0.5 | D56: h/semana | E56: Cada semana sem coaching = meio dia de produtividade subótima
B57: Custo/hora do vendedor | C57: =IF(AND(ISNUMBER(C39),ISNUMBER(Premissas!C8)),C39*Premissas!C8/Premissas!C9,) | D57: R$/h | E57: salário × encargos / jornada mensal (Premissas!C9)
B58: COI Fila Anual | C58: =IF(AND(ISNUMBER(C54),ISNUMBER(C55),ISNUMBER(C56),ISNUMBER(C57)),C54*C55*C56*C57*12,) | D58: R$/ano | E58: vendedores_fila × semanas_espera × horas_perdidas × custo_hora × 12
B60: DIAGNÓSTICO — PROBLEMA ESTRUTURAL DE CAPACIDADE DO GERENTE (bandwidth)
B61: Parâmetro | C61: Valor | D61: Unidade | E61: Fonte / Observação
B62: Gerentes de treinamento | C62: =IF(ISNUMBER(Equipes!C22),Equipes!C22,1) | D62: gerentes | E62: Dado do cliente (aba Equipes). Default: 1
B63: Horas de coaching/gerente/mês (capacidade) | C63: =IF(ISNUMBER(Equipes!C23),Equipes!C23,16) | D63: h/mês | E63: Equipes!C23 = horas que o gerente dedica. Default: 16h (2 semanas)
B64: Capacidade total de coaching/mês | C64: =C62*C63 | D64: h/mês | E64: gerentes × horas/gerente
B65: Demanda necessária de coaching/mês | C65: =IF(ISNUMBER(C8),C8*2,) | D65: h/mês | E65: 2h/mês por vendedor (benchmark MySalesCoach: mínimo para impacto)
B66: Gap de capacidade (bandwidth) | C66: =IF(AND(ISNUMBER(C65),ISNUMBER(C64)),C65-C64,) | D66: h/mês | E66: demanda - capacidade. Negativo = OK; Positivo = déficit estrutural
B67: % da demanda não atendida | C67: =IF(AND(ISNUMBER(C66),ISNUMBER(C65),C65<>0),IF(C66>0,C66/C65,0),) | D67: % | E67: Se > 50%, o problema é estrutural: não é falta de vontade, é falta de capacidade
B69: RESUMO — CUSTO TOTAL DA INAÇÃO (COI TOTAL)
B70: Componente | C70: COI Anual (R$) | D70: % do COI Total | E70: Observação
B71: Perda de receita por subdesempenho (sub-performance) | C71: =C21 | D71: =IF(C$76<>0,C71/C$76,0) | E71: Maior COI: vendedores não treinados performam pior
B72: Custo de rampa estendida | C72: =C31 | D72: =IF(C$76<>0,C72/C$76,0) | E72: Novos vendedores demoram mais sem coaching estruturado
B73: Custo de turnover | C73: =C42 | D73: =IF(C$76<>0,C73/C$76,0) | E73: Reps sem coaching ficam 2× mais propensos a sair
B74: Imposto do aprendizado em vivo | C74: =C50 | D74: =IF(C$76<>0,C74/C$76,0) | E74: Negócios perdidos por "sem decisão" que coaching resolveria
B75: Custo da fila de espera | C75: =C58 | D75: =IF(C$76<>0,C75/C$76,0) | E75: Vendedores esperando coaching = produtividade perdida
B76: COI TOTAL ANUAL | C76: =SUM(C71:C75) | D76: 1 | E76: Soma de todos os custos da inação. Este é o preço de NÃO investir em coaching.
B79: MÉTRICA DE URGÊNCIA — COI vs INVESTIMENTO PERFECTING
B80: Métrica | C80: Valor | D80: Unidade | E80: Interpretação
B81: COI Total Anual | C81: =C76 | D81: R$/ano | E81: Quanto custa não agir por 1 ano
B82: COI Mensal | C82: =C76/12 | D82: R$/mês | E82: Custo da inação por mês — benchmark vs mensalidade Perfecting
B83: Mensalidade Perfecting (estimada) | C83: =Conta!C22 | D83: R$/mês | E83: Cross-reference da aba Conta
B84: Razão COI / Investimento | C84: =IF(AND(ISNUMBER(C76),N(Conta!C22)>0),C76/(Conta!C22*12),) | D84: × | E84: COI anual / investimento anual. >1 = inação custa mais que agir
B85: COI diário | C85: =C76/365 | D85: R$/dia | E85: Custo por dia de inação. Cada dia sem ação = este valor perdido
B87: REFERÊNCIAS E BENCHMARKS UTILIZADOS
B88: Fonte | C88: Dado | D88: Ano | E88: Detalhe
B89: MySalesCoach | C89: 29pp gap quota | D89: 2026 | E89: Semanal 76% vs trimestral 47%. 3.700+ profissionais. State of Sales Coaching 2026
B90: MySalesCoach | C90: 45% coaching below avg | D90: 2026 | E90: Subida de 29% (2025) para 45% (2026). Gap de execução, não atitude
B91: MySalesCoach | C91: 41% never/rarely coached | D91: 2026 | E91: Apesar de 64% dos líderes acharem que coacham mais
B92: MySalesCoach | C92: 40pp retention gap | D92: 2026 | E92: SDRs com coaching: 74% ficam. Sem coaching: 34% ficam
B93: Ebsta | C93: Rampa: 4.3 para 5.7 meses | D93: 2024 | E93: Aumento de 1,4 meses no tempo de rampa B2B
B94: Gartner | C94: 6 in 10 lack coaching | D94: 2024 | E94: 60% dos funcionários não recebem coaching necessário no trabalho
B95: Dixon/McKenna HBR | C95: 40-60% negócios = sem decisão (no decision) | D95: 2019 | E95: Maioria das perdas B2B não vai para concorrência, vai para status quo
B96: Deloitte | C96: Span of control: 9.7 | D96: 2023 | E96: Média Fortune 500, subiu de 7.1 em 2010
B97: CareerTrainer.ai | C97: Rampa média: 5.3 meses | D97: 2026 | E97: AE 4.4m, SDR 3.2m. Benchmark global consolidado
B99: NOTAS METODOLÓGICAS
B100: ① O COI é ADITIVO ao ROI — não substitui. ROI responde "quanto retorno?". COI responde "quanto custa não fazer nada?"
B101: ② Haircuts conservadores (50%) aplicados em cada dimensão para evitar overclaim, seguindo a mesma lógica anti-otimismo do Motor
B102: ③ Células em azul (fonte) são inputs editáveis — ajuste para refletir a realidade do cliente. Células em verde são cross-references de outras abas
B103: ④ A Dimensão 1 (Gap de Cobertura) é o indicador-chave: se gap de cobertura < 20%, o COI será pequeno. Se > 60%, o COI explode
B104: ⑤ O diagnóstico de bandwidth (Seção 7) prova que o problema é estrutural: não é falta de vontade do gerente, é falta de capacidade
B105: ⑥ Todos os dados de pesquisa são de fontes públicas e auditáveis. Os inputs podem ser substituídos por dados do cliente quando disponíveis

Sheet Conta
B1: Conta — Precificação, ROI e Payback Consolidados
B2: Cálculo em tempo real | Resultados só aparecem quando todas as equipes ativas estão completas
B3: Precificação escalonada com piso, decomposição de valor, série de 12 meses, verificação de realismo e alerta de contrato.
B6: CONFIGURAÇÃO E STATUS
B7: Contrato | C7: =Equipes!$C8
B8: Meses | C8: =IFERROR(INDEX(Premissas!$C$49:$C$52,MATCH(Equipes!$C8,Premissas!$B$49:$B$52,0)),"")
B9: Desconto | C9: =IFERROR(INDEX(Premissas!$D$49:$D$52,MATCH(Equipes!$C8,Premissas!$B$49:$B$52,0)),0)
B10: Cenário | C10: =Equipes!$C7
B11: Equipes ativas | C11: =COUNTIF(Motor!C7:L7,TRUE())
B12: Equipes completas | C12: =COUNTIF(Motor!C15:L15,TRUE())
B13: Horas da conta (h/mês) | C13: =SUM(Motor!C20:L20)
B14: Conta completa? | C14: =AND($C$11>0,$C$11=$C$12)
B16: DETALHAMENTO DA PRECIFICAÇÃO ESCADONADA
B17: Tier 1 (até 262h) | C17: =MIN($C$13,Premissas!$C$30) | D17: =Premissas!$E$30 | E17: =C17*D17
B18: Tier 2 (263-573h) | C18: =MAX(0,MIN($C$13,Premissas!$C$31)-Premissas!$C$30) | D18: =Premissas!$E$31 | E18: =C18*D18
B19: Tier 3 (574-1243h) | C19: =MAX(0,MIN($C$13,Premissas!$C$32)-Premissas!$C$31) | D19: =Premissas!$E$32 | E19: =C19*D19
B20: Tier 4 (1244h+) | C20: =MAX(0,$C$13-Premissas!$C$32) | D20: =Premissas!$E$33 | E20: =C20*D20
B21: Preço bruto (mês) | C21: =SUM(E17:E20)
B22: MENSALIDADE (com piso) | C22: =IF($C$14,MAX($C$21*(1-$C$9),Premissas!$C$21),"")
B23: Piso ativo? (R$13.000) | C23: =IF($C$14,$C$21*(1-$C$9)<Premissas!$C$21,FALSE())
B24: Taxa efetiva (R$/h) | C24: =IF(AND(ISNUMBER($C$22),$C$13>0),$C$22/$C$13,"")
B25: Tier marginal (R$/h) | C25: =IF($C$13>Premissas!$C$32,Premissas!$E$33,IF($C$13>Premissas!$C$31,Premissas!$E$32,IF($C$13>Premissas!$C$30,Premissas!$E$31,Premissas!$E$30)))
B26: Investimento anual | C26: =IF(ISNUMBER($C$22),$C$22*12,"")
B28: RESULTADO CONSOLIDADO
B29: VALOR ANUAL DA CONTA | C29: =IF($C$14,SUM(Motor!C72:L72),"")
B30: ROI CONSOLIDADO
B31: PAYBACK (meses)
B32: Payback excede contrato? | C32: =IF(ISNUMBER($C$31),$C$31>$C$8,FALSE()) | E32: Auditoria A-01: payback usa investimento anualizado; contratos curtos podem mostrar payback > duração do contrato
B34: DECOMPOSIÇÃO DE VALOR
B35: Eficiência (ano) | C35: =IF($C$14,SUM(Motor!C41:L41),"")
B36: Ganho de ticket (ano) | C36: =IF($C$14,SUM(Motor!C60:L60),"")
B37: Margem de rampa (ano) | C37: =IF($C$14,SUM(Motor!C61:L61),"")
B38: Ganho de conversão (ano) | C38: =IF($C$14,SUM(Motor!C62:L62),"")
B39: Ganho de ciclo (ano) | C39: =IF($C$14,SUM(Motor!C68:L68),"")
B40: Verificação: soma = valor anual | C40: =IF($C$14,IF(ABS(SUM(C35:C39)-$C$29)<0.01,"OK","ERROR"),"")
B42: OPERAÇÕES CONSOLIDADAS
B43: Total de vendedores | C43: =IF($C$14,SUM(Equipes!C21:L21),"")
B44: Total de assentos efetivos | C44: =IF($C$14,SUM(Motor!C19:L19),"")
B45: Cobertura da conta | C45: =IF($C$14,MIN(1,$C$44/$C$43),"")
B46: Preço médio por assento (mês) | C46: =IF(AND(ISNUMBER($C$22),N($C$44)>0),$C$22/$C$44,"")
B47: Investimento médio por vendedor/dia | C47: =IF(ISNUMBER(C46),C46/Premissas!$C$19,"")
B48: Retorno médio por assento/dia | C48: =IF(AND(ISNUMBER($C$29),N($C$44)>0),$C$29/$C$44/Premissas!$C$20,"")
B50: VERIFICAÇÃO DE REALISMO
B51: Margem anual atual | C51: =IF($C$14,SUM(Motor!C74:L74),"")
B52: G — ganhos de performance (ano)
B53: Verificação (G / margem anual)
B54: Alerta (> 25%)? | C54: =IF(ISNUMBER($C$53),$C$53>Premissas!$C$26,FALSE()) | E54: Ganhos não devem exceder 25% da margem atual
B56: SÉRIE CUMULATIVA DE 12 MESES (distribuição linear; apenas apresentação)
B57: Mês | C57: Valor Cumul. | D57: Invest. Cumul. | E57: Pago?
B58: 0 | C58: =IF($C$14,$C$29/12*B58,"") | D58: =IF($C$14,$C$22*B58,"") | E58: =IF(ISNUMBER(C58),IF(C58>=D58,"SIM","Ainda não"),"")
B59: 1 | C59: =IF($C$14,$C$29/12*B59,"") | D59: =IF($C$14,$C$22*B59,"") | E59: =IF(ISNUMBER(C59),IF(C59>=D59,"SIM","Ainda não"),"")
B60: 2 | C60: =IF($C$14,$C$29/12*B60,"") | D60: =IF($C$14,$C$22*B60,"") | E60: =IF(ISNUMBER(C60),IF(C60>=D60,"SIM","Ainda não"),"")
B61: 3 | C61: =IF($C$14,$C$29/12*B61,"") | D61: =IF($C$14,$C$22*B61,"") | E61: =IF(ISNUMBER(C61),IF(C61>=D61,"SIM","Ainda não"),"")
B62: 4 | C62: =IF($C$14,$C$29/12*B62,"") | D62: =IF($C$14,$C$22*B62,"") | E62: =IF(ISNUMBER(C62),IF(C62>=D62,"SIM","Ainda não"),"")
B63: 5 | C63: =IF($C$14,$C$29/12*B63,"") | D63: =IF($C$14,$C$22*B63,"") | E63: =IF(ISNUMBER(C63),IF(C63>=D63,"SIM","Ainda não"),"")
B64: 6 | C64: =IF($C$14,$C$29/12*B64,"") | D64: =IF($C$14,$C$22*B64,"") | E64: =IF(ISNUMBER(C64),IF(C64>=D64,"SIM","Ainda não"),"")
B65: 7 | C65: =IF($C$14,$C$29/12*B65,"") | D65: =IF($C$14,$C$22*B65,"") | E65: =IF(ISNUMBER(C65),IF(C65>=D65,"SIM","Ainda não"),"")
B66: 8 | C66: =IF($C$14,$C$29/12*B66,"") | D66: =IF($C$14,$C$22*B66,"") | E66: =IF(ISNUMBER(C66),IF(C66>=D66,"SIM","Ainda não"),"")
B67: 9 | C67: =IF($C$14,$C$29/12*B67,"") | D67: =IF($C$14,$C$22*B67,"") | E67: =IF(ISNUMBER(C67),IF(C67>=D67,"SIM","Ainda não"),"")
B68: 10 | C68: =IF($C$14,$C$29/12*B68,"") | D68: =IF($C$14,$C$22*B68,"") | E68: =IF(ISNUMBER(C68),IF(C68>=D68,"SIM","Ainda não"),"")
B69: 11 | C69: =IF($C$14,$C$29/12*B69,"") | D69: =IF($C$14,$C$22*B69,"") | E69: =IF(ISNUMBER(C69),IF(C69>=D69,"SIM","Ainda não"),"")
B70: 12 | C70: =IF($C$14,$C$29/12*B70,"") | D70: =IF($C$14,$C$22*B70,"") | E70: =IF(ISNUMBER(C70),IF(C70>=D70,"SIM","Ainda não"),"")

Sheet Comparação de Cenários
B1: Comparação de Cenários — Conservador / Realista / Otimista
B2: Todos os 3 cenários lado a lado | Baseado nos dados atuais das equipes
B3: Mostra como ROI, payback e valor mudam entre cenários. Usa mesmos dados da equipe; apenas deltas mudam.
B6: PARÂMETROS DE CENÁRIO
B7: Métrica | C7: Conservador | D7: Realista | E7: Otimista
B8: Delta ticket | C8: =Premissas!$C$43 | D8: =Premissas!$C$44 | E8: =Premissas!$C$45
B9: Delta rampa | C9: =Premissas!$D$43 | D9: =Premissas!$D$44 | E9: =Premissas!$D$45
B10: Delta ciclo | C10: =Premissas!$E$43 | D10: =Premissas!$E$44 | E10: =Premissas!$E$45
B11: Delta conversão (p.p.) | C11: =Premissas!$F$43 | D11: =Premissas!$F$44 | E11: =Premissas!$F$45
B13: RESULTADOS DE CENÁRIO
B14: Métrica | C14: Conservador | D14: Realista | E14: Otimista
B15: Eficiência (igual) | C15: =SUM(Motor!C41:L41) | D15: =SUM(Motor!C41:L41) | E15: =SUM(Motor!C41:L41)
B16: Ganho de ticket | C16: =N(Equipes!C29)*Premissas!$C$43*12*N(Equipes!C32)*N(Motor!C34)+N(Equipes!D29)*Premissas!$C$43*12*N(Equipes!D32)*N(Motor!D34)+N(Equipes!E29)*Premissas!$C$43*12*N(Equipes!E32)*N(Motor!E34)+N(Equipes!F29)*Premissas!$C$43*12*N(Equipes!F32)*N(Motor!F34)+N(Equipes!G29)*Premissas!$C$43*12*N(Equipes!G32)*N(Motor!G34)+N(Equipes!H29)*Premissas!$C$43*12*N(Equipes!H32)*N(Motor!H34)+N(Equipes!I29)*Premissas!$C$43*12*N(Equipes!I32)*N(Motor!I34)+N(Equipes!J29)*Premissas!$C$43*12*N(Equipes!J32)*N(Motor!J34)+N(Equipes!K29)*Premissas!$C$43*12*N(Equipes!K32)*N(Motor!K34)+N(Equipes!L29)*Premissas!$C$43*12*N(Equipes!L32)*N(Motor!L34) | D16: =N(Equipes!C29)*Premissas!$C$44*12*N(Equipes!C32)*N(Motor!C34)+N(Equipes!D29)*Premissas!$C$44*12*N(Equipes!D32)*N(Motor!D34)+N(Equipes!E29)*Premissas!$C$44*12*N(Equipes!E32)*N(Motor!E34)+N(Equipes!F29)*Premissas!$C$44*12*N(Equipes!F32)*N(Motor!F34)+N(Equipes!G29)*Premissas!$C$44*12*N(Equipes!G32)*N(Motor!G34)+N(Equipes!H29)*Premissas!$C$44*12*N(Equipes!H32)*N(Motor!H34)+N(Equipes!I29)*Premissas!$C$44*12*N(Equipes!I32)*N(Motor!I34)+N(Equipes!J29)*Premissas!$C$44*12*N(Equipes!J32)*N(Motor!J34)+N(Equipes!K29)*Premissas!$C$44*12*N(Equipes!K32)*N(Motor!K34)+N(Equipes!L29)*Premissas!$C$44*12*N(Equipes!L32)*N(Motor!L34) | E16: =N(Equipes!C29)*Premissas!$C$45*12*N(Equipes!C32)*N(Motor!C34)+N(Equipes!D29)*Premissas!$C$45*12*N(Equipes!D32)*N(Motor!D34)+N(Equipes!E29)*Premissas!$C$45*12*N(Equipes!E32)*N(Motor!E34)+N(Equipes!F29)*Premissas!$C$45*12*N(Equipes!F32)*N(Motor!F34)+N(Equipes!G29)*Premissas!$C$45*12*N(Equipes!G32)*N(Motor!G34)+N(Equipes!H29)*Premissas!$C$45*12*N(Equipes!H32)*N(Motor!H34)+N(Equipes!I29)*Premissas!$C$45*12*N(Equipes!I32)*N(Motor!I34)+N(Equipes!J29)*Premissas!$C$45*12*N(Equipes!J32)*N(Motor!J34)+N(Equipes!K29)*Premissas!$C$45*12*N(Equipes!K32)*N(Motor!K34)+N(Equipes!L29)*Premissas!$C$45*12*N(Equipes!L32)*N(Motor!L34)
B17: Margem de rampa | C17: =N(Equipes!C35)*Premissas!$D$43*N(Motor!C22)*N(Equipes!C36)*N(Equipes!C32)*Premissas!$C$12*N(Motor!C34)+N(Equipes!D35)*Premissas!$D$43*N(Motor!D22)*N(Equipes!D36)*N(Equipes!D32)*Premissas!$C$12*N(Motor!D34)+N(Equipes!E35)*Premissas!$D$43*N(Motor!E22)*N(Equipes!E36)*N(Equipes!E32)*Premissas!$C$12*N(Motor!E34)+N(Equipes!F35)*Premissas!$D$43*N(Motor!F22)*N(Equipes!F36)*N(Equipes!F32)*Premissas!$C$12*N(Motor!F34)+N(Equipes!G35)*Premissas!$D$43*N(Motor!G22)*N(Equipes!G36)*N(Equipes!G32)*Premissas!$C$12*N(Motor!G34)+N(Equipes!H35)*Premissas!$D$43*N(Motor!H22)*N(Equipes!H36)*N(Equipes!H32)*Premissas!$C$12*N(Motor!H34)+N(Equipes!I35)*Premissas!$D$43*N(Motor!I22)*N(Equipes!I36)*N(Equipes!I32)*Premissas!$C$12*N(Motor!I34)+N(Equipes!J35)*Premissas!$D$43*N(Motor!J22)*N(Equipes!J36)*N(Equipes!J32)*Premissas!$C$12*N(Motor!J34)+N(Equipes!K35)*Premissas!$D$43*N(Motor!K22)*N(Equipes!K36)*N(Equipes!K32)*Premissas!$C$12*N(Motor!K34)+N(Equipes!L35)*Premissas!$D$43*N(Motor!L22)*N(Equipes!L36)*N(Equipes!L32)*Premissas!$C$12*N(Motor!L34) | D17: =N(Equipes!C35)*Premissas!$D$44*N(Motor!C22)*N(Equipes!C36)*N(Equipes!C32)*Premissas!$C$12*N(Motor!C34)+N(Equipes!D35)*Premissas!$D$44*N(Motor!D22)*N(Equipes!D36)*N(Equipes!D32)*Premissas!$C$12*N(Motor!D34)+N(Equipes!E35)*Premissas!$D$44*N(Motor!E22)*N(Equipes!E36)*N(Equipes!E32)*Premissas!$C$12*N(Motor!E34)+N(Equipes!F35)*Premissas!$D$44*N(Motor!F22)*N(Equipes!F36)*N(Equipes!F32)*Premissas!$C$12*N(Motor!F34)+N(Equipes!G35)*Premissas!$D$44*N(Motor!G22)*N(Equipes!G36)*N(Equipes!G32)*Premissas!$C$12*N(Motor!G34)+N(Equipes!H35)*Premissas!$D$44*N(Motor!H22)*N(Equipes!H36)*N(Equipes!H32)*Premissas!$C$12*N(Motor!H34)+N(Equipes!I35)*Premissas!$D$44*N(Motor!I22)*N(Equipes!I36)*N(Equipes!I32)*Premissas!$C$12*N(Motor!I34)+N(Equipes!J35)*Premissas!$D$44*N(Motor!J22)*N(Equipes!J36)*N(Equipes!J32)*Premissas!$C$12*N(Motor!J34)+N(Equipes!K35)*Premissas!$D$44*N(Motor!K22)*N(Equipes!K36)*N(Equipes!K32)*Premissas!$C$12*N(Motor!K34)+N(Equipes!L35)*Premissas!$D$44*N(Motor!L22)*N(Equipes!L36)*N(Equipes!L32)*Premissas!$C$12*N(Motor!L34) | E17: =N(Equipes!C35)*Premissas!$D$45*N(Motor!C22)*N(Equipes!C36)*N(Equipes!C32)*Premissas!$C$12*N(Motor!C34)+N(Equipes!D35)*Premissas!$D$45*N(Motor!D22)*N(Equipes!D36)*N(Equipes!D32)*Premissas!$C$12*N(Motor!D34)+N(Equipes!E35)*Premissas!$D$45*N(Motor!E22)*N(Equipes!E36)*N(Equipes!E32)*Premissas!$C$12*N(Motor!E34)+N(Equipes!F35)*Premissas!$D$45*N(Motor!F22)*N(Equipes!F36)*N(Equipes!F32)*Premissas!$C$12*N(Motor!F34)+N(Equipes!G35)*Premissas!$D$45*N(Motor!G22)*N(Equipes!G36)*N(Equipes!G32)*Premissas!$C$12*N(Motor!G34)+N(Equipes!H35)*Premissas!$D$45*N(Motor!H22)*N(Equipes!H36)*N(Equipes!H32)*Premissas!$C$12*N(Motor!H34)+N(Equipes!I35)*Premissas!$D$45*N(Motor!I22)*N(Equipes!I36)*N(Equipes!I32)*Premissas!$C$12*N(Motor!I34)+N(Equipes!J35)*Premissas!$D$45*N(Motor!J22)*N(Equipes!J36)*N(Equipes!J32)*Premissas!$C$12*N(Motor!J34)+N(Equipes!K35)*Premissas!$D$45*N(Motor!K22)*N(Equipes!K36)*N(Equipes!K32)*Premissas!$C$12*N(Motor!K34)+N(Equipes!L35)*Premissas!$D$45*N(Motor!L22)*N(Equipes!L36)*N(Equipes!L32)*Premissas!$C$12*N(Motor!L34)
B18: Ganho de conversão | C18: =IFERROR((N(Equipes!C29)/N(Equipes!C30))/N(Motor!C47)*Premissas!$F$43/100*N(Equipes!C30)*N(Equipes!C32)*12*Premissas!$C$14*N(Motor!C34),0)+IFERROR((N(Equipes!D29)/N(Equipes!D30))/N(Motor!D47)*Premissas!$F$43/100*N(Equipes!D30)*N(Equipes!D32)*12*Premissas!$C$14*N(Motor!D34),0)+IFERROR((N(Equipes!E29)/N(Equipes!E30))/N(Motor!E47)*Premissas!$F$43/100*N(Equipes!E30)*N(Equipes!E32)*12*Premissas!$C$14*N(Motor!E34),0)+IFERROR((N(Equipes!F29)/N(Equipes!F30))/N(Motor!F47)*Premissas!$F$43/100*N(Equipes!F30)*N(Equipes!F32)*12*Premissas!$C$14*N(Motor!F34),0)+IFERROR((N(Equipes!G29)/N(Equipes!G30))/N(Motor!G47)*Premissas!$F$43/100*N(Equipes!G30)*N(Equipes!G32)*12*Premissas!$C$14*N(Motor!G34),0)+IFERROR((N(Equipes!H29)/N(Equipes!H30))/N(Motor!H47)*Premissas!$F$43/100*N(Equipes!H30)*N(Equipes!H32)*12*Premissas!$C$14*N(Motor!H34),0)+IFERROR((N(Equipes!I29)/N(Equipes!I30))/N(Motor!I47)*Premissas!$F$43/100*N(Equipes!I30)*N(Equipes!I32)*12*Premissas!$C$14*N(Motor!I34),0)+IFERROR((N(Equipes!J29)/N(Equipes!J30))/N(Motor!J47)*Premissas!$F$43/100*N(Equipes!J30)*N(Equipes!J32)*12*Premissas!$C$14*N(Motor!J34),0)+IFERROR((N(Equipes!K29)/N(Equipes!K30))/N(Motor!K47)*Premissas!$F$43/100*N(Equipes!K30)*N(Equipes!K32)*12*Premissas!$C$14*N(Motor!K34),0)+IFERROR((N(Equipes!L29)/N(Equipes!L30))/N(Motor!L47)*Premissas!$F$43/100*N(Equipes!L30)*N(Equipes!L32)*12*Premissas!$C$14*N(Motor!L34),0) | D18: =IFERROR((N(Equipes!C29)/N(Equipes!C30))/N(Motor!C47)*Premissas!$F$44/100*N(Equipes!C30)*N(Equipes!C32)*12*Premissas!$C$14*N(Motor!C34),0)+IFERROR((N(Equipes!D29)/N(Equipes!D30))/N(Motor!D47)*Premissas!$F$44/100*N(Equipes!D30)*N(Equipes!D32)*12*Premissas!$C$14*N(Motor!D34),0)+IFERROR((N(Equipes!E29)/N(Equipes!E30))/N(Motor!E47)*Premissas!$F$44/100*N(Equipes!E30)*N(Equipes!E32)*12*Premissas!$C$14*N(Motor!E34),0)+IFERROR((N(Equipes!F29)/N(Equipes!F30))/N(Motor!F47)*Premissas!$F$44/100*N(Equipes!F30)*N(Equipes!F32)*12*Premissas!$C$14*N(Motor!F34),0)+IFERROR((N(Equipes!G29)/N(Equipes!G30))/N(Motor!G47)*Premissas!$F$44/100*N(Equipes!G30)*N(Equipes!G32)*12*Premissas!$C$14*N(Motor!G34),0)+IFERROR((N(Equipes!H29)/N(Equipes!H30))/N(Motor!H47)*Premissas!$F$44/100*N(Equipes!H30)*N(Equipes!H32)*12*Premissas!$C$14*N(Motor!H34),0)+IFERROR((N(Equipes!I29)/N(Equipes!I30))/N(Motor!I47)*Premissas!$F$44/100*N(Equipes!I30)*N(Equipes!I32)*12*Premissas!$C$14*N(Motor!I34),0)+IFERROR((N(Equipes!J29)/N(Equipes!J30))/N(Motor!J47)*Premissas!$F$44/100*N(Equipes!J30)*N(Equipes!J32)*12*Premissas!$C$14*N(Motor!J34),0)+IFERROR((N(Equipes!K29)/N(Equipes!K30))/N(Motor!K47)*Premissas!$F$44/100*N(Equipes!K30)*N(Equipes!K32)*12*Premissas!$C$14*N(Motor!K34),0)+IFERROR((N(Equipes!L29)/N(Equipes!L30))/N(Motor!L47)*Premissas!$F$44/100*N(Equipes!L30)*N(Equipes!L32)*12*Premissas!$C$14*N(Motor!L34),0) | E18: =IFERROR((N(Equipes!C29)/N(Equipes!C30))/N(Motor!C47)*Premissas!$F$45/100*N(Equipes!C30)*N(Equipes!C32)*12*Premissas!$C$14*N(Motor!C34),0)+IFERROR((N(Equipes!D29)/N(Equipes!D30))/N(Motor!D47)*Premissas!$F$45/100*N(Equipes!D30)*N(Equipes!D32)*12*Premissas!$C$14*N(Motor!D34),0)+IFERROR((N(Equipes!E29)/N(Equipes!E30))/N(Motor!E47)*Premissas!$F$45/100*N(Equipes!E30)*N(Equipes!E32)*12*Premissas!$C$14*N(Motor!E34),0)+IFERROR((N(Equipes!F29)/N(Equipes!F30))/N(Motor!F47)*Premissas!$F$45/100*N(Equipes!F30)*N(Equipes!F32)*12*Premissas!$C$14*N(Motor!F34),0)+IFERROR((N(Equipes!G29)/N(Equipes!G30))/N(Motor!G47)*Premissas!$F$45/100*N(Equipes!G30)*N(Equipes!G32)*12*Premissas!$C$14*N(Motor!G34),0)+IFERROR((N(Equipes!H29)/N(Equipes!H30))/N(Motor!H47)*Premissas!$F$45/100*N(Equipes!H30)*N(Equipes!H32)*12*Premissas!$C$14*N(Motor!H34),0)+IFERROR((N(Equipes!I29)/N(Equipes!I30))/N(Motor!I47)*Premissas!$F$45/100*N(Equipes!I30)*N(Equipes!I32)*12*Premissas!$C$14*N(Motor!I34),0)+IFERROR((N(Equipes!J29)/N(Equipes!J30))/N(Motor!J47)*Premissas!$F$45/100*N(Equipes!J30)*N(Equipes!J32)*12*Premissas!$C$14*N(Motor!J34),0)+IFERROR((N(Equipes!K29)/N(Equipes!K30))/N(Motor!K47)*Premissas!$F$45/100*N(Equipes!K30)*N(Equipes!K32)*12*Premissas!$C$14*N(Motor!K34),0)+IFERROR((N(Equipes!L29)/N(Equipes!L30))/N(Motor!L47)*Premissas!$F$45/100*N(Equipes!L30)*N(Equipes!L32)*12*Premissas!$C$14*N(Motor!L34),0)
B19: Ganho de ciclo | C19: =SUM(Motor!C68:L68) | D19: =IF(Motor!C15,IF(AND(N(Motor!C52)>0,N(Equipes!C46)>0),MIN(IF(AND(D10>0,D10<1),(Equipes!C29/Equipes!C30)*(1/(1-D10)-1),0),MAX(0,Equipes!C46-(Equipes!C29/Equipes!C30)/Motor!C47)*Motor!C47)*Equipes!C30*Equipes!C32*12*Premissas!$C$13*Motor!C34,0),"") | E19: =IF(Motor!C15,IF(AND(N(Motor!C52)>0,N(Equipes!C46)>0),MIN(IF(AND(E10>0,E10<1),(Equipes!C29/Equipes!C30)*(1/(1-E10)-1),0),MAX(0,Equipes!C46-(Equipes!C29/Equipes!C30)/Motor!C47)*Motor!C47)*Equipes!C30*Equipes!C32*12*Premissas!$C$13*Motor!C34,0),"")
B20: VALOR ANUAL TOTAL | C20: =SUM(C15:C19) | D20: =SUM(D15:D19) | E20: =SUM(E15:E19)
B21: Mensalidade | C21: =Conta!$C$22 | D21: =Conta!$C$22 | E21: =Conta!$C$22
B22: Investimento anual | C22: =Conta!$C$26 | D22: =Conta!$C$26 | E22: =Conta!$C$26
B23: ROI | C23: =IF(AND(ISNUMBER(C20),N(C22)>0),C20/C22,"") | D23: =IF(AND(ISNUMBER(D20),N(D22)>0),D20/D22,"") | E23: =IF(AND(ISNUMBER(E20),N(E22)>0),E20/E22,"")
B24: Payback (meses) | C24: =IF(AND(ISNUMBER(C22),N(C20)>0),C22/C20*12,"") | D24: =IF(AND(ISNUMBER(D22),N(D20)>0),D22/D20*12,"") | E24: =IF(AND(ISNUMBER(E22),N(E20)>0),E22/E20*12,"")
